{"v":"5.7.8","fr":29.9700012207031,"ip":0,"op":25.0000010182709,"w":800,"h":800,"nm":"Gif","ddd":0,"assets":[],"layers":[{"ddd":0,"ind":1,"ty":4,"nm":"Group 9095 contornos 10","sr":1,"ks":{"o":{"a":0,"k":100,"ix":11},"r":{"a":0,"k":100,"ix":10},"p":{"a":0,"k":[274,525,0],"ix":2,"l":2},"a":{"a":0,"k":[421,298,0],"ix":1,"l":2},"s":{"a":0,"k":[62.233,62.233,100],"ix":6,"l":2}},"ao":0,"shapes":[{"ty":"gr","it":[{"ind":0,"ty":"sh","ix":1,"ks":{"a":0,"k":{"i":[[0,0],[0,0]],"o":[[0,0],[0,0]],"v":[[8.74,1.23],[-8.74,-1.23]],"c":false},"ix":2},"nm":"Caminho 1","mn":"ADBE Vector Shape - Group","hd":false},{"ty":"st","c":{"a":0,"k":[1,1,1,1],"ix":3},"o":{"a":0,"k":100,"ix":4},"w":{"a":0,"k":6.14,"ix":5},"lc":2,"lj":1,"ml":4,"bm":0,"nm":"Traçado 1","mn":"ADBE Vector Graphic - Stroke","hd":false},{"ty":"tr","p":{"a":0,"k":[334.978,279.855],"ix":2},"a":{"a":0,"k":[0,0],"ix":1},"s":{"a":0,"k":[100,100],"ix":3},"r":{"a":0,"k":0,"ix":6},"o":{"a":0,"k":100,"ix":7},"sk":{"a":0,"k":0,"ix":4},"sa":{"a":0,"k":0,"ix":5},"nm":"Transformar"}],"nm":"Grupo 1","np":2,"cix":2,"bm":0,"ix":1,"mn":"ADBE Vector Group","hd":false},{"ty":"gr","it":[{"ind":0,"ty":"sh","ix":1,"ks":{"a":0,"k":{"i":[[0,0],[3.562,-3.997]],"o":[[-4.329,3.343],[0,0]],"v":[[6.23,-5.711],[-6.229,5.711]],"c":false},"ix":2},"nm":"Caminho 1","mn":"ADBE Vector Shape - Group","hd":false},{"ty":"st","c":{"a":0,"k":[1,1,1,1],"ix":3},"o":{"a":0,"k":100,"ix":4},"w":{"a":0,"k":6.14,"ix":5},"lc":2,"lj":1,"ml":4,"bm":0,"nm":"Traçado 1","mn":"ADBE Vector Graphic - Stroke","hd":false},{"ty":"tr","p":{"a":0,"k":[340.809,318.268],"ix":2},"a":{"a":0,"k":[0,0],"ix":1},"s":{"a":0,"k":[100,100],"ix":3},"r":{"a":0,"k":0,"ix":6},"o":{"a":0,"k":100,"ix":7},"sk":{"a":0,"k":0,"ix":4},"sa":{"a":0,"k":0,"ix":5},"nm":"Transformar"}],"nm":"Grupo 2","np":2,"cix":2,"bm":0,"ix":2,"mn":"ADBE Vector Group","hd":false},{"ty":"gr","it":[{"ind":0,"ty":"sh","ix":1,"ks":{"a":0,"k":{"i":[[2.692,-20.244],[-19.782,-2.785],[-2.717,20.263],[19.826,2.791]],"o":[[-2.646,19.756],[20.134,2.834],[2.653,-19.8],[-20.153,-2.859]],"v":[[-35.786,-4.656],[-5.065,35.793],[35.779,4.655],[5.076,-35.768]],"c":true},"ix":2},"nm":"Caminho 1","mn":"ADBE Vector Shape - Group","hd":false},{"ty":"fl","c":{"a":0,"k":[0.830999995213,0.917999985639,0.961000031116,1],"ix":4},"o":{"a":0,"k":100,"ix":5},"r":1,"bm":0,"nm":"Preenchimento 1","mn":"ADBE Vector Graphic - Fill","hd":false},{"ty":"tr","p":{"a":0,"k":[396.612,290.571],"ix":2},"a":{"a":0,"k":[0,0],"ix":1},"s":{"a":0,"k":[100,100],"ix":3},"r":{"a":0,"k":0,"ix":6},"o":{"a":0,"k":100,"ix":7},"sk":{"a":0,"k":0,"ix":4},"sa":{"a":0,"k":0,"ix":5},"nm":"Transformar"}],"nm":"Grupo 3","np":2,"cix":2,"bm":0,"ix":3,"mn":"ADBE Vector Group","hd":false},{"ty":"gr","it":[{"ind":0,"ty":"sh","ix":1,"ks":{"a":0,"k":{"i":[[-34.205,-8.044],[-16.33,6.012],[1.95,39.372],[38.716,9.306],[3.747,0.904],[20.235,-21.727],[-9.965,-32.823]],"o":[[16.846,2.85],[36.847,-13.574],[-1.968,-39.599],[-3.748,-0.905],[-29.189,-1.662],[-23.337,25.107],[10.167,33.405]],"v":[[-16.744,88.408],[32.983,85.039],[92.113,-4.22],[23.387,-86.88],[12.124,-89.597],[-63.19,-61.606],[-84.098,26.154]],"c":true},"ix":2},"nm":"Caminho 1","mn":"ADBE Vector Shape - Group","hd":false},{"ty":"fl","c":{"a":0,"k":[0.2,0.255000005984,0.317999985639,1],"ix":4},"o":{"a":0,"k":100,"ix":5},"r":1,"bm":0,"nm":"Preenchimento 1","mn":"ADBE Vector Graphic - Fill","hd":false},{"ty":"tr","p":{"a":0,"k":[395.189,290.444],"ix":2},"a":{"a":0,"k":[0,0],"ix":1},"s":{"a":0,"k":[100,100],"ix":3},"r":{"a":0,"k":0,"ix":6},"o":{"a":0,"k":100,"ix":7},"sk":{"a":0,"k":0,"ix":4},"sa":{"a":0,"k":0,"ix":5},"nm":"Transformar"}],"nm":"Grupo 4","np":2,"cix":2,"bm":0,"ix":4,"mn":"ADBE Vector Group","hd":false}],"ip":0,"op":6.00000024438501,"st":0,"bm":0},{"ddd":0,"ind":2,"ty":4,"nm":"Group 9095 contornos 2","sr":1,"ks":{"o":{"a":0,"k":100,"ix":11},"r":{"a":0,"k":100,"ix":10},"p":{"a":0,"k":[498,527,0],"ix":2,"l":2},"a":{"a":0,"k":[421,298,0],"ix":1,"l":2},"s":{"a":0,"k":[62.233,62.233,100],"ix":6,"l":2}},"ao":0,"shapes":[{"ty":"gr","it":[{"ind":0,"ty":"sh","ix":1,"ks":{"a":0,"k":{"i":[[0,0],[0,0]],"o":[[0,0],[0,0]],"v":[[8.74,1.23],[-8.74,-1.23]],"c":false},"ix":2},"nm":"Caminho 1","mn":"ADBE Vector Shape - Group","hd":false},{"ty":"st","c":{"a":0,"k":[1,1,1,1],"ix":3},"o":{"a":0,"k":100,"ix":4},"w":{"a":0,"k":6.14,"ix":5},"lc":2,"lj":1,"ml":4,"bm":0,"nm":"Traçado 1","mn":"ADBE Vector Graphic - Stroke","hd":false},{"ty":"tr","p":{"a":0,"k":[334.978,279.855],"ix":2},"a":{"a":0,"k":[0,0],"ix":1},"s":{"a":0,"k":[100,100],"ix":3},"r":{"a":0,"k":0,"ix":6},"o":{"a":0,"k":100,"ix":7},"sk":{"a":0,"k":0,"ix":4},"sa":{"a":0,"k":0,"ix":5},"nm":"Transformar"}],"nm":"Grupo 1","np":2,"cix":2,"bm":0,"ix":1,"mn":"ADBE Vector Group","hd":false},{"ty":"gr","it":[{"ind":0,"ty":"sh","ix":1,"ks":{"a":0,"k":{"i":[[0,0],[3.562,-3.997]],"o":[[-4.329,3.343],[0,0]],"v":[[6.23,-5.711],[-6.229,5.711]],"c":false},"ix":2},"nm":"Caminho 1","mn":"ADBE Vector Shape - Group","hd":false},{"ty":"st","c":{"a":0,"k":[1,1,1,1],"ix":3},"o":{"a":0,"k":100,"ix":4},"w":{"a":0,"k":6.14,"ix":5},"lc":2,"lj":1,"ml":4,"bm":0,"nm":"Traçado 1","mn":"ADBE Vector Graphic - Stroke","hd":false},{"ty":"tr","p":{"a":0,"k":[340.809,318.268],"ix":2},"a":{"a":0,"k":[0,0],"ix":1},"s":{"a":0,"k":[100,100],"ix":3},"r":{"a":0,"k":0,"ix":6},"o":{"a":0,"k":100,"ix":7},"sk":{"a":0,"k":0,"ix":4},"sa":{"a":0,"k":0,"ix":5},"nm":"Transformar"}],"nm":"Grupo 2","np":2,"cix":2,"bm":0,"ix":2,"mn":"ADBE Vector Group","hd":false},{"ty":"gr","it":[{"ind":0,"ty":"sh","ix":1,"ks":{"a":0,"k":{"i":[[2.692,-20.244],[-19.782,-2.785],[-2.717,20.263],[19.826,2.791]],"o":[[-2.646,19.756],[20.134,2.834],[2.653,-19.8],[-20.153,-2.859]],"v":[[-35.786,-4.656],[-5.065,35.793],[35.779,4.655],[5.076,-35.768]],"c":true},"ix":2},"nm":"Caminho 1","mn":"ADBE Vector Shape - Group","hd":false},{"ty":"fl","c":{"a":0,"k":[0.830999995213,0.917999985639,0.961000031116,1],"ix":4},"o":{"a":0,"k":100,"ix":5},"r":1,"bm":0,"nm":"Preenchimento 1","mn":"ADBE Vector Graphic - Fill","hd":false},{"ty":"tr","p":{"a":0,"k":[396.612,290.571],"ix":2},"a":{"a":0,"k":[0,0],"ix":1},"s":{"a":0,"k":[100,100],"ix":3},"r":{"a":0,"k":0,"ix":6},"o":{"a":0,"k":100,"ix":7},"sk":{"a":0,"k":0,"ix":4},"sa":{"a":0,"k":0,"ix":5},"nm":"Transformar"}],"nm":"Grupo 3","np":2,"cix":2,"bm":0,"ix":3,"mn":"ADBE Vector Group","hd":false},{"ty":"gr","it":[{"ind":0,"ty":"sh","ix":1,"ks":{"a":0,"k":{"i":[[-34.205,-8.044],[-16.33,6.012],[1.95,39.372],[38.716,9.306],[3.747,0.904],[20.235,-21.727],[-9.965,-32.823]],"o":[[16.846,2.85],[36.847,-13.574],[-1.968,-39.599],[-3.748,-0.905],[-29.189,-1.662],[-23.337,25.107],[10.167,33.405]],"v":[[-16.744,88.408],[32.983,85.039],[92.113,-4.22],[23.387,-86.88],[12.124,-89.597],[-63.19,-61.606],[-84.098,26.154]],"c":true},"ix":2},"nm":"Caminho 1","mn":"ADBE Vector Shape - Group","hd":false},{"ty":"fl","c":{"a":0,"k":[0.2,0.255000005984,0.317999985639,1],"ix":4},"o":{"a":0,"k":100,"ix":5},"r":1,"bm":0,"nm":"Preenchimento 1","mn":"ADBE Vector Graphic - Fill","hd":false},{"ty":"tr","p":{"a":0,"k":[395.189,290.444],"ix":2},"a":{"a":0,"k":[0,0],"ix":1},"s":{"a":0,"k":[100,100],"ix":3},"r":{"a":0,"k":0,"ix":6},"o":{"a":0,"k":100,"ix":7},"sk":{"a":0,"k":0,"ix":4},"sa":{"a":0,"k":0,"ix":5},"nm":"Transformar"}],"nm":"Grupo 4","np":2,"cix":2,"bm":0,"ix":4,"mn":"ADBE Vector Group","hd":false}],"ip":0,"op":6.00000024438501,"st":0,"bm":0},{"ddd":0,"ind":3,"ty":4,"nm":"Group 9095 contornos 11","sr":1,"ks":{"o":{"a":0,"k":100,"ix":11},"r":{"a":0,"k":200,"ix":10},"p":{"a":0,"k":[270,503,0],"ix":2,"l":2},"a":{"a":0,"k":[421,298,0],"ix":1,"l":2},"s":{"a":0,"k":[62.233,62.233,100],"ix":6,"l":2}},"ao":0,"shapes":[{"ty":"gr","it":[{"ind":0,"ty":"sh","ix":1,"ks":{"a":0,"k":{"i":[[0,0],[0,0]],"o":[[0,0],[0,0]],"v":[[8.74,1.23],[-8.74,-1.23]],"c":false},"ix":2},"nm":"Caminho 1","mn":"ADBE Vector Shape - Group","hd":false},{"ty":"st","c":{"a":0,"k":[1,1,1,1],"ix":3},"o":{"a":0,"k":100,"ix":4},"w":{"a":0,"k":6.14,"ix":5},"lc":2,"lj":1,"ml":4,"bm":0,"nm":"Traçado 1","mn":"ADBE Vector Graphic - Stroke","hd":false},{"ty":"tr","p":{"a":0,"k":[334.978,279.855],"ix":2},"a":{"a":0,"k":[0,0],"ix":1},"s":{"a":0,"k":[100,100],"ix":3},"r":{"a":0,"k":0,"ix":6},"o":{"a":0,"k":100,"ix":7},"sk":{"a":0,"k":0,"ix":4},"sa":{"a":0,"k":0,"ix":5},"nm":"Transformar"}],"nm":"Grupo 1","np":2,"cix":2,"bm":0,"ix":1,"mn":"ADBE Vector Group","hd":false},{"ty":"gr","it":[{"ind":0,"ty":"sh","ix":1,"ks":{"a":0,"k":{"i":[[0,0],[3.562,-3.997]],"o":[[-4.329,3.343],[0,0]],"v":[[6.23,-5.711],[-6.229,5.711]],"c":false},"ix":2},"nm":"Caminho 1","mn":"ADBE Vector Shape - Group","hd":false},{"ty":"st","c":{"a":0,"k":[1,1,1,1],"ix":3},"o":{"a":0,"k":100,"ix":4},"w":{"a":0,"k":6.14,"ix":5},"lc":2,"lj":1,"ml":4,"bm":0,"nm":"Traçado 1","mn":"ADBE Vector Graphic - Stroke","hd":false},{"ty":"tr","p":{"a":0,"k":[340.809,318.268],"ix":2},"a":{"a":0,"k":[0,0],"ix":1},"s":{"a":0,"k":[100,100],"ix":3},"r":{"a":0,"k":0,"ix":6},"o":{"a":0,"k":100,"ix":7},"sk":{"a":0,"k":0,"ix":4},"sa":{"a":0,"k":0,"ix":5},"nm":"Transformar"}],"nm":"Grupo 2","np":2,"cix":2,"bm":0,"ix":2,"mn":"ADBE Vector Group","hd":false},{"ty":"gr","it":[{"ind":0,"ty":"sh","ix":1,"ks":{"a":0,"k":{"i":[[2.692,-20.244],[-19.782,-2.785],[-2.717,20.263],[19.826,2.791]],"o":[[-2.646,19.756],[20.134,2.834],[2.653,-19.8],[-20.153,-2.859]],"v":[[-35.786,-4.656],[-5.065,35.793],[35.779,4.655],[5.076,-35.768]],"c":true},"ix":2},"nm":"Caminho 1","mn":"ADBE Vector Shape - Group","hd":false},{"ty":"fl","c":{"a":0,"k":[0.830999995213,0.917999985639,0.961000031116,1],"ix":4},"o":{"a":0,"k":100,"ix":5},"r":1,"bm":0,"nm":"Preenchimento 1","mn":"ADBE Vector Graphic - Fill","hd":false},{"ty":"tr","p":{"a":0,"k":[396.612,290.571],"ix":2},"a":{"a":0,"k":[0,0],"ix":1},"s":{"a":0,"k":[100,100],"ix":3},"r":{"a":0,"k":0,"ix":6},"o":{"a":0,"k":100,"ix":7},"sk":{"a":0,"k":0,"ix":4},"sa":{"a":0,"k":0,"ix":5},"nm":"Transformar"}],"nm":"Grupo 3","np":2,"cix":2,"bm":0,"ix":3,"mn":"ADBE Vector Group","hd":false},{"ty":"gr","it":[{"ind":0,"ty":"sh","ix":1,"ks":{"a":0,"k":{"i":[[-34.205,-8.044],[-16.33,6.012],[1.95,39.372],[38.716,9.306],[3.747,0.904],[20.235,-21.727],[-9.965,-32.823]],"o":[[16.846,2.85],[36.847,-13.574],[-1.968,-39.599],[-3.748,-0.905],[-29.189,-1.662],[-23.337,25.107],[10.167,33.405]],"v":[[-16.744,88.408],[32.983,85.039],[92.113,-4.22],[23.387,-86.88],[12.124,-89.597],[-63.19,-61.606],[-84.098,26.154]],"c":true},"ix":2},"nm":"Caminho 1","mn":"ADBE Vector Shape - Group","hd":false},{"ty":"fl","c":{"a":0,"k":[0.2,0.255000005984,0.317999985639,1],"ix":4},"o":{"a":0,"k":100,"ix":5},"r":1,"bm":0,"nm":"Preenchimento 1","mn":"ADBE Vector Graphic - Fill","hd":false},{"ty":"tr","p":{"a":0,"k":[395.189,290.444],"ix":2},"a":{"a":0,"k":[0,0],"ix":1},"s":{"a":0,"k":[100,100],"ix":3},"r":{"a":0,"k":0,"ix":6},"o":{"a":0,"k":100,"ix":7},"sk":{"a":0,"k":0,"ix":4},"sa":{"a":0,"k":0,"ix":5},"nm":"Transformar"}],"nm":"Grupo 4","np":2,"cix":2,"bm":0,"ix":4,"mn":"ADBE Vector Group","hd":false}],"ip":6.00000024438501,"op":13.0000005295009,"st":6.00000024438501,"bm":0},{"ddd":0,"ind":4,"ty":4,"nm":"Group 9095 contornos 4","sr":1,"ks":{"o":{"a":0,"k":100,"ix":11},"r":{"a":0,"k":200,"ix":10},"p":{"a":0,"k":[491,505,0],"ix":2,"l":2},"a":{"a":0,"k":[421,298,0],"ix":1,"l":2},"s":{"a":0,"k":[62.233,62.233,100],"ix":6,"l":2}},"ao":0,"shapes":[{"ty":"gr","it":[{"ind":0,"ty":"sh","ix":1,"ks":{"a":0,"k":{"i":[[0,0],[0,0]],"o":[[0,0],[0,0]],"v":[[8.74,1.23],[-8.74,-1.23]],"c":false},"ix":2},"nm":"Caminho 1","mn":"ADBE Vector Shape - Group","hd":false},{"ty":"st","c":{"a":0,"k":[1,1,1,1],"ix":3},"o":{"a":0,"k":100,"ix":4},"w":{"a":0,"k":6.14,"ix":5},"lc":2,"lj":1,"ml":4,"bm":0,"nm":"Traçado 1","mn":"ADBE Vector Graphic - Stroke","hd":false},{"ty":"tr","p":{"a":0,"k":[334.978,279.855],"ix":2},"a":{"a":0,"k":[0,0],"ix":1},"s":{"a":0,"k":[100,100],"ix":3},"r":{"a":0,"k":0,"ix":6},"o":{"a":0,"k":100,"ix":7},"sk":{"a":0,"k":0,"ix":4},"sa":{"a":0,"k":0,"ix":5},"nm":"Transformar"}],"nm":"Grupo 1","np":2,"cix":2,"bm":0,"ix":1,"mn":"ADBE Vector Group","hd":false},{"ty":"gr","it":[{"ind":0,"ty":"sh","ix":1,"ks":{"a":0,"k":{"i":[[0,0],[3.562,-3.997]],"o":[[-4.329,3.343],[0,0]],"v":[[6.23,-5.711],[-6.229,5.711]],"c":false},"ix":2},"nm":"Caminho 1","mn":"ADBE Vector Shape - Group","hd":false},{"ty":"st","c":{"a":0,"k":[1,1,1,1],"ix":3},"o":{"a":0,"k":100,"ix":4},"w":{"a":0,"k":6.14,"ix":5},"lc":2,"lj":1,"ml":4,"bm":0,"nm":"Traçado 1","mn":"ADBE Vector Graphic - Stroke","hd":false},{"ty":"tr","p":{"a":0,"k":[340.809,318.268],"ix":2},"a":{"a":0,"k":[0,0],"ix":1},"s":{"a":0,"k":[100,100],"ix":3},"r":{"a":0,"k":0,"ix":6},"o":{"a":0,"k":100,"ix":7},"sk":{"a":0,"k":0,"ix":4},"sa":{"a":0,"k":0,"ix":5},"nm":"Transformar"}],"nm":"Grupo 2","np":2,"cix":2,"bm":0,"ix":2,"mn":"ADBE Vector Group","hd":false},{"ty":"gr","it":[{"ind":0,"ty":"sh","ix":1,"ks":{"a":0,"k":{"i":[[2.692,-20.244],[-19.782,-2.785],[-2.717,20.263],[19.826,2.791]],"o":[[-2.646,19.756],[20.134,2.834],[2.653,-19.8],[-20.153,-2.859]],"v":[[-35.786,-4.656],[-5.065,35.793],[35.779,4.655],[5.076,-35.768]],"c":true},"ix":2},"nm":"Caminho 1","mn":"ADBE Vector Shape - Group","hd":false},{"ty":"fl","c":{"a":0,"k":[0.830999995213,0.917999985639,0.961000031116,1],"ix":4},"o":{"a":0,"k":100,"ix":5},"r":1,"bm":0,"nm":"Preenchimento 1","mn":"ADBE Vector Graphic - Fill","hd":false},{"ty":"tr","p":{"a":0,"k":[396.612,290.571],"ix":2},"a":{"a":0,"k":[0,0],"ix":1},"s":{"a":0,"k":[100,100],"ix":3},"r":{"a":0,"k":0,"ix":6},"o":{"a":0,"k":100,"ix":7},"sk":{"a":0,"k":0,"ix":4},"sa":{"a":0,"k":0,"ix":5},"nm":"Transformar"}],"nm":"Grupo 3","np":2,"cix":2,"bm":0,"ix":3,"mn":"ADBE Vector Group","hd":false},{"ty":"gr","it":[{"ind":0,"ty":"sh","ix":1,"ks":{"a":0,"k":{"i":[[-34.205,-8.044],[-16.33,6.012],[1.95,39.372],[38.716,9.306],[3.747,0.904],[20.235,-21.727],[-9.965,-32.823]],"o":[[16.846,2.85],[36.847,-13.574],[-1.968,-39.599],[-3.748,-0.905],[-29.189,-1.662],[-23.337,25.107],[10.167,33.405]],"v":[[-16.744,88.408],[32.983,85.039],[92.113,-4.22],[23.387,-86.88],[12.124,-89.597],[-63.19,-61.606],[-84.098,26.154]],"c":true},"ix":2},"nm":"Caminho 1","mn":"ADBE Vector Shape - Group","hd":false},{"ty":"fl","c":{"a":0,"k":[0.2,0.255000005984,0.317999985639,1],"ix":4},"o":{"a":0,"k":100,"ix":5},"r":1,"bm":0,"nm":"Preenchimento 1","mn":"ADBE Vector Graphic - Fill","hd":false},{"ty":"tr","p":{"a":0,"k":[395.189,290.444],"ix":2},"a":{"a":0,"k":[0,0],"ix":1},"s":{"a":0,"k":[100,100],"ix":3},"r":{"a":0,"k":0,"ix":6},"o":{"a":0,"k":100,"ix":7},"sk":{"a":0,"k":0,"ix":4},"sa":{"a":0,"k":0,"ix":5},"nm":"Transformar"}],"nm":"Grupo 4","np":2,"cix":2,"bm":0,"ix":4,"mn":"ADBE Vector Group","hd":false}],"ip":6.00000024438501,"op":13.0000005295009,"st":6.00000024438501,"bm":0},{"ddd":0,"ind":5,"ty":4,"nm":"Group 9095 contornos 12","sr":1,"ks":{"o":{"a":0,"k":100,"ix":11},"r":{"a":0,"k":300,"ix":10},"p":{"a":0,"k":[294,501,0],"ix":2,"l":2},"a":{"a":0,"k":[421,298,0],"ix":1,"l":2},"s":{"a":0,"k":[62.233,62.233,100],"ix":6,"l":2}},"ao":0,"shapes":[{"ty":"gr","it":[{"ind":0,"ty":"sh","ix":1,"ks":{"a":0,"k":{"i":[[0,0],[0,0]],"o":[[0,0],[0,0]],"v":[[8.74,1.23],[-8.74,-1.23]],"c":false},"ix":2},"nm":"Caminho 1","mn":"ADBE Vector Shape - Group","hd":false},{"ty":"st","c":{"a":0,"k":[1,1,1,1],"ix":3},"o":{"a":0,"k":100,"ix":4},"w":{"a":0,"k":6.14,"ix":5},"lc":2,"lj":1,"ml":4,"bm":0,"nm":"Traçado 1","mn":"ADBE Vector Graphic - Stroke","hd":false},{"ty":"tr","p":{"a":0,"k":[334.978,279.855],"ix":2},"a":{"a":0,"k":[0,0],"ix":1},"s":{"a":0,"k":[100,100],"ix":3},"r":{"a":0,"k":0,"ix":6},"o":{"a":0,"k":100,"ix":7},"sk":{"a":0,"k":0,"ix":4},"sa":{"a":0,"k":0,"ix":5},"nm":"Transformar"}],"nm":"Grupo 1","np":2,"cix":2,"bm":0,"ix":1,"mn":"ADBE Vector Group","hd":false},{"ty":"gr","it":[{"ind":0,"ty":"sh","ix":1,"ks":{"a":0,"k":{"i":[[0,0],[3.562,-3.997]],"o":[[-4.329,3.343],[0,0]],"v":[[6.23,-5.711],[-6.229,5.711]],"c":false},"ix":2},"nm":"Caminho 1","mn":"ADBE Vector Shape - Group","hd":false},{"ty":"st","c":{"a":0,"k":[1,1,1,1],"ix":3},"o":{"a":0,"k":100,"ix":4},"w":{"a":0,"k":6.14,"ix":5},"lc":2,"lj":1,"ml":4,"bm":0,"nm":"Traçado 1","mn":"ADBE Vector Graphic - Stroke","hd":false},{"ty":"tr","p":{"a":0,"k":[340.809,318.268],"ix":2},"a":{"a":0,"k":[0,0],"ix":1},"s":{"a":0,"k":[100,100],"ix":3},"r":{"a":0,"k":0,"ix":6},"o":{"a":0,"k":100,"ix":7},"sk":{"a":0,"k":0,"ix":4},"sa":{"a":0,"k":0,"ix":5},"nm":"Transformar"}],"nm":"Grupo 2","np":2,"cix":2,"bm":0,"ix":2,"mn":"ADBE Vector Group","hd":false},{"ty":"gr","it":[{"ind":0,"ty":"sh","ix":1,"ks":{"a":0,"k":{"i":[[2.692,-20.244],[-19.782,-2.785],[-2.717,20.263],[19.826,2.791]],"o":[[-2.646,19.756],[20.134,2.834],[2.653,-19.8],[-20.153,-2.859]],"v":[[-35.786,-4.656],[-5.065,35.793],[35.779,4.655],[5.076,-35.768]],"c":true},"ix":2},"nm":"Caminho 1","mn":"ADBE Vector Shape - Group","hd":false},{"ty":"fl","c":{"a":0,"k":[0.830999995213,0.917999985639,0.961000031116,1],"ix":4},"o":{"a":0,"k":100,"ix":5},"r":1,"bm":0,"nm":"Preenchimento 1","mn":"ADBE Vector Graphic - Fill","hd":false},{"ty":"tr","p":{"a":0,"k":[396.612,290.571],"ix":2},"a":{"a":0,"k":[0,0],"ix":1},"s":{"a":0,"k":[100,100],"ix":3},"r":{"a":0,"k":0,"ix":6},"o":{"a":0,"k":100,"ix":7},"sk":{"a":0,"k":0,"ix":4},"sa":{"a":0,"k":0,"ix":5},"nm":"Transformar"}],"nm":"Grupo 3","np":2,"cix":2,"bm":0,"ix":3,"mn":"ADBE Vector Group","hd":false},{"ty":"gr","it":[{"ind":0,"ty":"sh","ix":1,"ks":{"a":0,"k":{"i":[[-34.205,-8.044],[-16.33,6.012],[1.95,39.372],[38.716,9.306],[3.747,0.904],[20.235,-21.727],[-9.965,-32.823]],"o":[[16.846,2.85],[36.847,-13.574],[-1.968,-39.599],[-3.748,-0.905],[-29.189,-1.662],[-23.337,25.107],[10.167,33.405]],"v":[[-16.744,88.408],[32.983,85.039],[92.113,-4.22],[23.387,-86.88],[12.124,-89.597],[-63.19,-61.606],[-84.098,26.154]],"c":true},"ix":2},"nm":"Caminho 1","mn":"ADBE Vector Shape - Group","hd":false},{"ty":"fl","c":{"a":0,"k":[0.2,0.255000005984,0.317999985639,1],"ix":4},"o":{"a":0,"k":100,"ix":5},"r":1,"bm":0,"nm":"Preenchimento 1","mn":"ADBE Vector Graphic - Fill","hd":false},{"ty":"tr","p":{"a":0,"k":[395.189,290.444],"ix":2},"a":{"a":0,"k":[0,0],"ix":1},"s":{"a":0,"k":[100,100],"ix":3},"r":{"a":0,"k":0,"ix":6},"o":{"a":0,"k":100,"ix":7},"sk":{"a":0,"k":0,"ix":4},"sa":{"a":0,"k":0,"ix":5},"nm":"Transformar"}],"nm":"Grupo 4","np":2,"cix":2,"bm":0,"ix":4,"mn":"ADBE Vector Group","hd":false}],"ip":13.0000005295009,"op":20.0000008146167,"st":16.0000006516934,"bm":0},{"ddd":0,"ind":6,"ty":4,"nm":"Group 9095 contornos 7","sr":1,"ks":{"o":{"a":0,"k":100,"ix":11},"r":{"a":0,"k":300,"ix":10},"p":{"a":0,"k":[516,503,0],"ix":2,"l":2},"a":{"a":0,"k":[421,298,0],"ix":1,"l":2},"s":{"a":0,"k":[62.233,62.233,100],"ix":6,"l":2}},"ao":0,"shapes":[{"ty":"gr","it":[{"ind":0,"ty":"sh","ix":1,"ks":{"a":0,"k":{"i":[[0,0],[0,0]],"o":[[0,0],[0,0]],"v":[[8.74,1.23],[-8.74,-1.23]],"c":false},"ix":2},"nm":"Caminho 1","mn":"ADBE Vector Shape - Group","hd":false},{"ty":"st","c":{"a":0,"k":[1,1,1,1],"ix":3},"o":{"a":0,"k":100,"ix":4},"w":{"a":0,"k":6.14,"ix":5},"lc":2,"lj":1,"ml":4,"bm":0,"nm":"Traçado 1","mn":"ADBE Vector Graphic - Stroke","hd":false},{"ty":"tr","p":{"a":0,"k":[334.978,279.855],"ix":2},"a":{"a":0,"k":[0,0],"ix":1},"s":{"a":0,"k":[100,100],"ix":3},"r":{"a":0,"k":0,"ix":6},"o":{"a":0,"k":100,"ix":7},"sk":{"a":0,"k":0,"ix":4},"sa":{"a":0,"k":0,"ix":5},"nm":"Transformar"}],"nm":"Grupo 1","np":2,"cix":2,"bm":0,"ix":1,"mn":"ADBE Vector Group","hd":false},{"ty":"gr","it":[{"ind":0,"ty":"sh","ix":1,"ks":{"a":0,"k":{"i":[[0,0],[3.562,-3.997]],"o":[[-4.329,3.343],[0,0]],"v":[[6.23,-5.711],[-6.229,5.711]],"c":false},"ix":2},"nm":"Caminho 1","mn":"ADBE Vector Shape - Group","hd":false},{"ty":"st","c":{"a":0,"k":[1,1,1,1],"ix":3},"o":{"a":0,"k":100,"ix":4},"w":{"a":0,"k":6.14,"ix":5},"lc":2,"lj":1,"ml":4,"bm":0,"nm":"Traçado 1","mn":"ADBE Vector Graphic - Stroke","hd":false},{"ty":"tr","p":{"a":0,"k":[340.809,318.268],"ix":2},"a":{"a":0,"k":[0,0],"ix":1},"s":{"a":0,"k":[100,100],"ix":3},"r":{"a":0,"k":0,"ix":6},"o":{"a":0,"k":100,"ix":7},"sk":{"a":0,"k":0,"ix":4},"sa":{"a":0,"k":0,"ix":5},"nm":"Transformar"}],"nm":"Grupo 2","np":2,"cix":2,"bm":0,"ix":2,"mn":"ADBE Vector Group","hd":false},{"ty":"gr","it":[{"ind":0,"ty":"sh","ix":1,"ks":{"a":0,"k":{"i":[[2.692,-20.244],[-19.782,-2.785],[-2.717,20.263],[19.826,2.791]],"o":[[-2.646,19.756],[20.134,2.834],[2.653,-19.8],[-20.153,-2.859]],"v":[[-35.786,-4.656],[-5.065,35.793],[35.779,4.655],[5.076,-35.768]],"c":true},"ix":2},"nm":"Caminho 1","mn":"ADBE Vector Shape - Group","hd":false},{"ty":"fl","c":{"a":0,"k":[0.830999995213,0.917999985639,0.961000031116,1],"ix":4},"o":{"a":0,"k":100,"ix":5},"r":1,"bm":0,"nm":"Preenchimento 1","mn":"ADBE Vector Graphic - Fill","hd":false},{"ty":"tr","p":{"a":0,"k":[396.612,290.571],"ix":2},"a":{"a":0,"k":[0,0],"ix":1},"s":{"a":0,"k":[100,100],"ix":3},"r":{"a":0,"k":0,"ix":6},"o":{"a":0,"k":100,"ix":7},"sk":{"a":0,"k":0,"ix":4},"sa":{"a":0,"k":0,"ix":5},"nm":"Transformar"}],"nm":"Grupo 3","np":2,"cix":2,"bm":0,"ix":3,"mn":"ADBE Vector Group","hd":false},{"ty":"gr","it":[{"ind":0,"ty":"sh","ix":1,"ks":{"a":0,"k":{"i":[[-34.205,-8.044],[-16.33,6.012],[1.95,39.372],[38.716,9.306],[3.747,0.904],[20.235,-21.727],[-9.965,-32.823]],"o":[[16.846,2.85],[36.847,-13.574],[-1.968,-39.599],[-3.748,-0.905],[-29.189,-1.662],[-23.337,25.107],[10.167,33.405]],"v":[[-16.744,88.408],[32.983,85.039],[92.113,-4.22],[23.387,-86.88],[12.124,-89.597],[-63.19,-61.606],[-84.098,26.154]],"c":true},"ix":2},"nm":"Caminho 1","mn":"ADBE Vector Shape - Group","hd":false},{"ty":"fl","c":{"a":0,"k":[0.2,0.255000005984,0.317999985639,1],"ix":4},"o":{"a":0,"k":100,"ix":5},"r":1,"bm":0,"nm":"Preenchimento 1","mn":"ADBE Vector Graphic - Fill","hd":false},{"ty":"tr","p":{"a":0,"k":[395.189,290.444],"ix":2},"a":{"a":0,"k":[0,0],"ix":1},"s":{"a":0,"k":[100,100],"ix":3},"r":{"a":0,"k":0,"ix":6},"o":{"a":0,"k":100,"ix":7},"sk":{"a":0,"k":0,"ix":4},"sa":{"a":0,"k":0,"ix":5},"nm":"Transformar"}],"nm":"Grupo 4","np":2,"cix":2,"bm":0,"ix":4,"mn":"ADBE Vector Group","hd":false}],"ip":13.0000005295009,"op":20.0000008146167,"st":16.0000006516934,"bm":0},{"ddd":0,"ind":7,"ty":4,"nm":"Group 9095 contornos 13","sr":1,"ks":{"o":{"a":0,"k":100,"ix":11},"r":{"a":0,"k":400,"ix":10},"p":{"a":0,"k":[292,527,0],"ix":2,"l":2},"a":{"a":0,"k":[421,298,0],"ix":1,"l":2},"s":{"a":0,"k":[62.233,62.233,100],"ix":6,"l":2}},"ao":0,"shapes":[{"ty":"gr","it":[{"ind":0,"ty":"sh","ix":1,"ks":{"a":0,"k":{"i":[[0,0],[0,0]],"o":[[0,0],[0,0]],"v":[[8.74,1.23],[-8.74,-1.23]],"c":false},"ix":2},"nm":"Caminho 1","mn":"ADBE Vector Shape - Group","hd":false},{"ty":"st","c":{"a":0,"k":[1,1,1,1],"ix":3},"o":{"a":0,"k":100,"ix":4},"w":{"a":0,"k":6.14,"ix":5},"lc":2,"lj":1,"ml":4,"bm":0,"nm":"Traçado 1","mn":"ADBE Vector Graphic - Stroke","hd":false},{"ty":"tr","p":{"a":0,"k":[334.978,279.855],"ix":2},"a":{"a":0,"k":[0,0],"ix":1},"s":{"a":0,"k":[100,100],"ix":3},"r":{"a":0,"k":0,"ix":6},"o":{"a":0,"k":100,"ix":7},"sk":{"a":0,"k":0,"ix":4},"sa":{"a":0,"k":0,"ix":5},"nm":"Transformar"}],"nm":"Grupo 1","np":2,"cix":2,"bm":0,"ix":1,"mn":"ADBE Vector Group","hd":false},{"ty":"gr","it":[{"ind":0,"ty":"sh","ix":1,"ks":{"a":0,"k":{"i":[[0,0],[3.562,-3.997]],"o":[[-4.329,3.343],[0,0]],"v":[[6.23,-5.711],[-6.229,5.711]],"c":false},"ix":2},"nm":"Caminho 1","mn":"ADBE Vector Shape - Group","hd":false},{"ty":"st","c":{"a":0,"k":[1,1,1,1],"ix":3},"o":{"a":0,"k":100,"ix":4},"w":{"a":0,"k":6.14,"ix":5},"lc":2,"lj":1,"ml":4,"bm":0,"nm":"Traçado 1","mn":"ADBE Vector Graphic - Stroke","hd":false},{"ty":"tr","p":{"a":0,"k":[340.809,318.268],"ix":2},"a":{"a":0,"k":[0,0],"ix":1},"s":{"a":0,"k":[100,100],"ix":3},"r":{"a":0,"k":0,"ix":6},"o":{"a":0,"k":100,"ix":7},"sk":{"a":0,"k":0,"ix":4},"sa":{"a":0,"k":0,"ix":5},"nm":"Transformar"}],"nm":"Grupo 2","np":2,"cix":2,"bm":0,"ix":2,"mn":"ADBE Vector Group","hd":false},{"ty":"gr","it":[{"ind":0,"ty":"sh","ix":1,"ks":{"a":0,"k":{"i":[[2.692,-20.244],[-19.782,-2.785],[-2.717,20.263],[19.826,2.791]],"o":[[-2.646,19.756],[20.134,2.834],[2.653,-19.8],[-20.153,-2.859]],"v":[[-35.786,-4.656],[-5.065,35.793],[35.779,4.655],[5.076,-35.768]],"c":true},"ix":2},"nm":"Caminho 1","mn":"ADBE Vector Shape - Group","hd":false},{"ty":"fl","c":{"a":0,"k":[0.830999995213,0.917999985639,0.961000031116,1],"ix":4},"o":{"a":0,"k":100,"ix":5},"r":1,"bm":0,"nm":"Preenchimento 1","mn":"ADBE Vector Graphic - Fill","hd":false},{"ty":"tr","p":{"a":0,"k":[396.612,290.571],"ix":2},"a":{"a":0,"k":[0,0],"ix":1},"s":{"a":0,"k":[100,100],"ix":3},"r":{"a":0,"k":0,"ix":6},"o":{"a":0,"k":100,"ix":7},"sk":{"a":0,"k":0,"ix":4},"sa":{"a":0,"k":0,"ix":5},"nm":"Transformar"}],"nm":"Grupo 3","np":2,"cix":2,"bm":0,"ix":3,"mn":"ADBE Vector Group","hd":false},{"ty":"gr","it":[{"ind":0,"ty":"sh","ix":1,"ks":{"a":0,"k":{"i":[[-34.205,-8.044],[-16.33,6.012],[1.95,39.372],[38.716,9.306],[3.747,0.904],[20.235,-21.727],[-9.965,-32.823]],"o":[[16.846,2.85],[36.847,-13.574],[-1.968,-39.599],[-3.748,-0.905],[-29.189,-1.662],[-23.337,25.107],[10.167,33.405]],"v":[[-16.744,88.408],[32.983,85.039],[92.113,-4.22],[23.387,-86.88],[12.124,-89.597],[-63.19,-61.606],[-84.098,26.154]],"c":true},"ix":2},"nm":"Caminho 1","mn":"ADBE Vector Shape - Group","hd":false},{"ty":"fl","c":{"a":0,"k":[0.2,0.255000005984,0.317999985639,1],"ix":4},"o":{"a":0,"k":100,"ix":5},"r":1,"bm":0,"nm":"Preenchimento 1","mn":"ADBE Vector Graphic - Fill","hd":false},{"ty":"tr","p":{"a":0,"k":[395.189,290.444],"ix":2},"a":{"a":0,"k":[0,0],"ix":1},"s":{"a":0,"k":[100,100],"ix":3},"r":{"a":0,"k":0,"ix":6},"o":{"a":0,"k":100,"ix":7},"sk":{"a":0,"k":0,"ix":4},"sa":{"a":0,"k":0,"ix":5},"nm":"Transformar"}],"nm":"Grupo 4","np":2,"cix":2,"bm":0,"ix":4,"mn":"ADBE Vector Group","hd":false}],"ip":20.0000008146167,"op":25.0000010182709,"st":20.0000008146167,"bm":0},{"ddd":0,"ind":8,"ty":4,"nm":"Group 9095 contornos","sr":1,"ks":{"o":{"a":0,"k":100,"ix":11},"r":{"a":0,"k":400,"ix":10},"p":{"a":0,"k":[512,527,0],"ix":2,"l":2},"a":{"a":0,"k":[421,298,0],"ix":1,"l":2},"s":{"a":0,"k":[62.233,62.233,100],"ix":6,"l":2}},"ao":0,"shapes":[{"ty":"gr","it":[{"ind":0,"ty":"sh","ix":1,"ks":{"a":0,"k":{"i":[[0,0],[0,0]],"o":[[0,0],[0,0]],"v":[[8.74,1.23],[-8.74,-1.23]],"c":false},"ix":2},"nm":"Caminho 1","mn":"ADBE Vector Shape - Group","hd":false},{"ty":"st","c":{"a":0,"k":[1,1,1,1],"ix":3},"o":{"a":0,"k":100,"ix":4},"w":{"a":0,"k":6.14,"ix":5},"lc":2,"lj":1,"ml":4,"bm":0,"nm":"Traçado 1","mn":"ADBE Vector Graphic - Stroke","hd":false},{"ty":"tr","p":{"a":0,"k":[334.978,279.855],"ix":2},"a":{"a":0,"k":[0,0],"ix":1},"s":{"a":0,"k":[100,100],"ix":3},"r":{"a":0,"k":0,"ix":6},"o":{"a":0,"k":100,"ix":7},"sk":{"a":0,"k":0,"ix":4},"sa":{"a":0,"k":0,"ix":5},"nm":"Transformar"}],"nm":"Grupo 1","np":2,"cix":2,"bm":0,"ix":1,"mn":"ADBE Vector Group","hd":false},{"ty":"gr","it":[{"ind":0,"ty":"sh","ix":1,"ks":{"a":0,"k":{"i":[[0,0],[3.562,-3.997]],"o":[[-4.329,3.343],[0,0]],"v":[[6.23,-5.711],[-6.229,5.711]],"c":false},"ix":2},"nm":"Caminho 1","mn":"ADBE Vector Shape - Group","hd":false},{"ty":"st","c":{"a":0,"k":[1,1,1,1],"ix":3},"o":{"a":0,"k":100,"ix":4},"w":{"a":0,"k":6.14,"ix":5},"lc":2,"lj":1,"ml":4,"bm":0,"nm":"Traçado 1","mn":"ADBE Vector Graphic - Stroke","hd":false},{"ty":"tr","p":{"a":0,"k":[340.809,318.268],"ix":2},"a":{"a":0,"k":[0,0],"ix":1},"s":{"a":0,"k":[100,100],"ix":3},"r":{"a":0,"k":0,"ix":6},"o":{"a":0,"k":100,"ix":7},"sk":{"a":0,"k":0,"ix":4},"sa":{"a":0,"k":0,"ix":5},"nm":"Transformar"}],"nm":"Grupo 2","np":2,"cix":2,"bm":0,"ix":2,"mn":"ADBE Vector Group","hd":false},{"ty":"gr","it":[{"ind":0,"ty":"sh","ix":1,"ks":{"a":0,"k":{"i":[[2.692,-20.244],[-19.782,-2.785],[-2.717,20.263],[19.826,2.791]],"o":[[-2.646,19.756],[20.134,2.834],[2.653,-19.8],[-20.153,-2.859]],"v":[[-35.786,-4.656],[-5.065,35.793],[35.779,4.655],[5.076,-35.768]],"c":true},"ix":2},"nm":"Caminho 1","mn":"ADBE Vector Shape - Group","hd":false},{"ty":"fl","c":{"a":0,"k":[0.830999995213,0.917999985639,0.961000031116,1],"ix":4},"o":{"a":0,"k":100,"ix":5},"r":1,"bm":0,"nm":"Preenchimento 1","mn":"ADBE Vector Graphic - Fill","hd":false},{"ty":"tr","p":{"a":0,"k":[396.612,290.571],"ix":2},"a":{"a":0,"k":[0,0],"ix":1},"s":{"a":0,"k":[100,100],"ix":3},"r":{"a":0,"k":0,"ix":6},"o":{"a":0,"k":100,"ix":7},"sk":{"a":0,"k":0,"ix":4},"sa":{"a":0,"k":0,"ix":5},"nm":"Transformar"}],"nm":"Grupo 3","np":2,"cix":2,"bm":0,"ix":3,"mn":"ADBE Vector Group","hd":false},{"ty":"gr","it":[{"ind":0,"ty":"sh","ix":1,"ks":{"a":0,"k":{"i":[[-34.205,-8.044],[-16.33,6.012],[1.95,39.372],[38.716,9.306],[3.747,0.904],[20.235,-21.727],[-9.965,-32.823]],"o":[[16.846,2.85],[36.847,-13.574],[-1.968,-39.599],[-3.748,-0.905],[-29.189,-1.662],[-23.337,25.107],[10.167,33.405]],"v":[[-16.744,88.408],[32.983,85.039],[92.113,-4.22],[23.387,-86.88],[12.124,-89.597],[-63.19,-61.606],[-84.098,26.154]],"c":true},"ix":2},"nm":"Caminho 1","mn":"ADBE Vector Shape - Group","hd":false},{"ty":"fl","c":{"a":0,"k":[0.2,0.255000005984,0.317999985639,1],"ix":4},"o":{"a":0,"k":100,"ix":5},"r":1,"bm":0,"nm":"Preenchimento 1","mn":"ADBE Vector Graphic - Fill","hd":false},{"ty":"tr","p":{"a":0,"k":[395.189,290.444],"ix":2},"a":{"a":0,"k":[0,0],"ix":1},"s":{"a":0,"k":[100,100],"ix":3},"r":{"a":0,"k":0,"ix":6},"o":{"a":0,"k":100,"ix":7},"sk":{"a":0,"k":0,"ix":4},"sa":{"a":0,"k":0,"ix":5},"nm":"Transformar"}],"nm":"Grupo 4","np":2,"cix":2,"bm":0,"ix":4,"mn":"ADBE Vector Group","hd":false}],"ip":20.0000008146167,"op":25.0000010182709,"st":20.0000008146167,"bm":0},{"ddd":0,"ind":9,"ty":4,"nm":"Group 7075 contornos 3","sr":1,"ks":{"o":{"a":0,"k":100,"ix":11},"r":{"a":0,"k":0,"ix":10},"p":{"a":1,"k":[{"i":{"x":0.833,"y":0.833},"o":{"x":0.167,"y":0.167},"t":3,"s":[400,428,0],"to":[0,-0.5,0],"ti":[0,0.5,0]},{"t":8.00000032584668,"s":[400,425,0]}],"ix":2,"l":2},"a":{"a":0,"k":[421,298,0],"ix":1,"l":2},"s":{"a":0,"k":[98.42,105.302,100],"ix":6,"l":2}},"ao":0,"shapes":[{"ty":"gr","it":[{"ind":0,"ty":"sh","ix":1,"ks":{"a":0,"k":{"i":[[-1.471,0.172],[-0.172,-1.471],[1.47,-0.171],[0.171,1.47]],"o":[[1.47,-0.171],[0.171,1.47],[-1.471,0.172],[-0.171,-1.471]],"v":[[-0.31,-2.663],[2.662,-0.31],[0.31,2.661],[-2.663,0.311]],"c":true},"ix":2},"nm":"Caminho 1","mn":"ADBE Vector Shape - Group","hd":false},{"ty":"fl","c":{"a":0,"k":[1,1,1,1],"ix":4},"o":{"a":0,"k":100,"ix":5},"r":1,"bm":0,"nm":"Preenchimento 1","mn":"ADBE Vector Graphic - Fill","hd":false},{"ty":"tr","p":{"a":0,"k":[520.932,226.257],"ix":2},"a":{"a":0,"k":[0,0],"ix":1},"s":{"a":0,"k":[100,100],"ix":3},"r":{"a":0,"k":0,"ix":6},"o":{"a":0,"k":100,"ix":7},"sk":{"a":0,"k":0,"ix":4},"sa":{"a":0,"k":0,"ix":5},"nm":"Transformar"}],"nm":"Grupo 1","np":2,"cix":2,"bm":0,"ix":1,"mn":"ADBE Vector Group","hd":false},{"ty":"gr","it":[{"ind":0,"ty":"sh","ix":1,"ks":{"a":0,"k":{"i":[[-2.94,0.343],[-0.342,-2.94],[2.941,-0.343],[0.344,2.941]],"o":[[2.94,-0.343],[0.343,2.941],[-2.94,0.343],[-0.343,-2.94]],"v":[[-0.621,-5.324],[5.324,-0.621],[0.621,5.324],[-5.324,0.621]],"c":true},"ix":2},"nm":"Caminho 1","mn":"ADBE Vector Shape - Group","hd":false},{"ty":"fl","c":{"a":0,"k":[1,1,1,1],"ix":4},"o":{"a":0,"k":100,"ix":5},"r":1,"bm":0,"nm":"Preenchimento 1","mn":"ADBE Vector Graphic - Fill","hd":false},{"ty":"tr","p":{"a":0,"k":[520.266,214.681],"ix":2},"a":{"a":0,"k":[0,0],"ix":1},"s":{"a":0,"k":[100,100],"ix":3},"r":{"a":0,"k":0,"ix":6},"o":{"a":0,"k":100,"ix":7},"sk":{"a":0,"k":0,"ix":4},"sa":{"a":0,"k":0,"ix":5},"nm":"Transformar"}],"nm":"Grupo 2","np":2,"cix":2,"bm":0,"ix":2,"mn":"ADBE Vector Group","hd":false},{"ty":"gr","it":[{"ind":0,"ty":"sh","ix":1,"ks":{"a":0,"k":{"i":[[-8.821,1.029],[-1.63,-13.967],[8.822,-1.029],[1.628,13.968]],"o":[[8.821,-1.029],[1.629,13.967],[-8.821,1.029],[-1.63,-13.966]],"v":[[-2.951,-25.29],[15.972,-1.863],[2.949,25.29],[-15.972,1.863]],"c":true},"ix":2},"nm":"Caminho 1","mn":"ADBE Vector Shape - Group","hd":false},{"ty":"fl","c":{"a":0,"k":[0.317999985639,0,0.097999999102,1],"ix":4},"o":{"a":0,"k":100,"ix":5},"r":1,"bm":0,"nm":"Preenchimento 1","mn":"ADBE Vector Graphic - Fill","hd":false},{"ty":"tr","p":{"a":0,"k":[512.265,220.661],"ix":2},"a":{"a":0,"k":[0,0],"ix":1},"s":{"a":0,"k":[100,100],"ix":3},"r":{"a":0,"k":0,"ix":6},"o":{"a":0,"k":100,"ix":7},"sk":{"a":0,"k":0,"ix":4},"sa":{"a":0,"k":0,"ix":5},"nm":"Transformar"}],"nm":"Grupo 3","np":2,"cix":2,"bm":0,"ix":3,"mn":"ADBE Vector Group","hd":false},{"ty":"gr","it":[{"ind":0,"ty":"sh","ix":1,"ks":{"a":0,"k":{"i":[[0,0],[1.565,-3.106],[0,-2.354]],"o":[[-3.458,1.103],[-1.093,2.16],[0,0]],"v":[[4.649,-6.571],[-3.555,-0.469],[-4.614,6.571]],"c":false},"ix":2},"nm":"Caminho 1","mn":"ADBE Vector Shape - Group","hd":false},{"ty":"st","c":{"a":0,"k":[0,0,0,1],"ix":3},"o":{"a":0,"k":100,"ix":4},"w":{"a":0,"k":3.755,"ix":5},"lc":2,"lj":1,"ml":4,"bm":0,"nm":"Traçado 1","mn":"ADBE Vector Graphic - Stroke","hd":false},{"ty":"tr","p":{"a":0,"k":[598.73,320.395],"ix":2},"a":{"a":0,"k":[0,0],"ix":1},"s":{"a":0,"k":[100,100],"ix":3},"r":{"a":0,"k":0,"ix":6},"o":{"a":0,"k":100,"ix":7},"sk":{"a":0,"k":0,"ix":4},"sa":{"a":0,"k":0,"ix":5},"nm":"Transformar"}],"nm":"Grupo 4","np":2,"cix":2,"bm":0,"ix":4,"mn":"ADBE Vector Group","hd":false},{"ty":"gr","it":[{"ind":0,"ty":"sh","ix":1,"ks":{"a":0,"k":{"i":[[0,0],[-8.545,-0.981],[-5.802,0],[-4.528,1.335]],"o":[[7.42,3.976],[5.757,0.66],[4.874,0],[0,0]],"v":[[-28.036,-3.921],[-3.765,3.261],[13.955,3.381],[28.036,0.804]],"c":false},"ix":2},"nm":"Caminho 1","mn":"ADBE Vector Shape - Group","hd":false},{"ty":"st","c":{"a":0,"k":[0,0,0,1],"ix":3},"o":{"a":0,"k":100,"ix":4},"w":{"a":0,"k":3.755,"ix":5},"lc":2,"lj":1,"ml":4,"bm":0,"nm":"Traçado 1","mn":"ADBE Vector Graphic - Stroke","hd":false},{"ty":"tr","p":{"a":0,"k":[626.158,325.255],"ix":2},"a":{"a":0,"k":[0,0],"ix":1},"s":{"a":0,"k":[100,100],"ix":3},"r":{"a":0,"k":0,"ix":6},"o":{"a":0,"k":100,"ix":7},"sk":{"a":0,"k":0,"ix":4},"sa":{"a":0,"k":0,"ix":5},"nm":"Transformar"}],"nm":"Grupo 5","np":2,"cix":2,"bm":0,"ix":5,"mn":"ADBE Vector Group","hd":false},{"ty":"gr","it":[{"ind":0,"ty":"sh","ix":1,"ks":{"a":0,"k":{"i":[[0,0],[-3.975,2.429],[-3.779,0]],"o":[[0,-4.359],[3.28,-2.004],[0,0]],"v":[[-8.214,7.51],[-1.643,-5.371],[8.214,-7.51]],"c":false},"ix":2},"nm":"Caminho 1","mn":"ADBE Vector Shape - Group","hd":false},{"ty":"st","c":{"a":0,"k":[0.317999985639,0,0.097999999102,1],"ix":3},"o":{"a":0,"k":100,"ix":4},"w":{"a":0,"k":3.755,"ix":5},"lc":2,"lj":1,"ml":4,"bm":0,"nm":"Traçado 1","mn":"ADBE Vector Graphic - Stroke","hd":false},{"ty":"tr","p":{"a":0,"k":[487.806,192.728],"ix":2},"a":{"a":0,"k":[0,0],"ix":1},"s":{"a":0,"k":[100,100],"ix":3},"r":{"a":0,"k":0,"ix":6},"o":{"a":0,"k":100,"ix":7},"sk":{"a":0,"k":0,"ix":4},"sa":{"a":0,"k":0,"ix":5},"nm":"Transformar"}],"nm":"Grupo 6","np":2,"cix":2,"bm":0,"ix":6,"mn":"ADBE Vector Group","hd":false},{"ty":"gr","it":[{"ind":0,"ty":"sh","ix":1,"ks":{"a":0,"k":{"i":[[-14.952,-0.011],[-14.285,-0.31],[-0.107,6.658],[0.28,20.408],[7.896,0.034],[9.11,0.447],[9.802,-13.213],[7.242,-17.99],[-8.269,-0.023]],"o":[[14.284,0],[9.163,0.206],[0.32,-20.408],[-0.093,-6.624],[-9.136,-0.035],[-18.379,-0.905],[-11.925,16.053],[-2.707,6.715],[14.938,0.057]],"v":[[0.9,41.527],[43.767,41.608],[57.038,30.87],[57.051,-30.366],[43.567,-40.828],[16.158,-40.909],[-25.521,-22.207],[-54.651,28.659],[-43.941,41.505]],"c":true},"ix":2},"nm":"Caminho 1","mn":"ADBE Vector Shape - Group","hd":false},{"ty":"fl","c":{"a":0,"k":[1,1,1,1],"ix":4},"o":{"a":0,"k":100,"ix":5},"r":1,"bm":0,"nm":"Preenchimento 1","mn":"ADBE Vector Graphic - Fill","hd":false},{"ty":"tr","p":{"a":0,"k":[292.779,208.376],"ix":2},"a":{"a":0,"k":[0,0],"ix":1},"s":{"a":0,"k":[100,100],"ix":3},"r":{"a":0,"k":0,"ix":6},"o":{"a":0,"k":100,"ix":7},"sk":{"a":0,"k":0,"ix":4},"sa":{"a":0,"k":0,"ix":5},"nm":"Transformar"}],"nm":"Grupo 7","np":2,"cix":2,"bm":0,"ix":7,"mn":"ADBE Vector Group","hd":false},{"ty":"gr","it":[{"ind":0,"ty":"sh","ix":1,"ks":{"a":0,"k":{"i":[[-22.143,0],[-22.541,0.035],[5.59,7.567],[12.639,15.237],[22.691,0.311],[20.07,-0.011],[0,-7.579],[-0.033,-20.048],[-10.848,0]],"o":[[22.54,0],[12.407,-0.011],[-11.544,-15.674],[-11.096,-13.355],[-20.052,-0.275],[-10.98,0.012],[-0.017,20.049],[0.016,7.625],[22.125,0.012]],"v":[[-2.164,42.268],[65.474,42.256],[78.809,27.685],[45.158,-28.936],[-7.805,-40.19],[-67.996,-40.247],[-84.367,-28.936],[-84.367,31.21],[-68.56,42.268]],"c":true},"ix":2},"nm":"Caminho 1","mn":"ADBE Vector Shape - Group","hd":false},{"ty":"fl","c":{"a":0,"k":[1,1,1,1],"ix":4},"o":{"a":0,"k":100,"ix":5},"r":1,"bm":0,"nm":"Preenchimento 1","mn":"ADBE Vector Graphic - Fill","hd":false},{"ty":"tr","p":{"a":0,"k":[468.228,207.715],"ix":2},"a":{"a":0,"k":[0,0],"ix":1},"s":{"a":0,"k":[100,100],"ix":3},"r":{"a":0,"k":0,"ix":6},"o":{"a":0,"k":100,"ix":7},"sk":{"a":0,"k":0,"ix":4},"sa":{"a":0,"k":0,"ix":5},"nm":"Transformar"}],"nm":"Grupo 8","np":2,"cix":2,"bm":0,"ix":8,"mn":"ADBE Vector Group","hd":false},{"ty":"gr","it":[{"ind":0,"ty":"sh","ix":1,"ks":{"a":0,"k":{"i":[[1.34,-15.205],[-10.12,0.034],[-0.072,7.467],[0.114,7.648],[8.252,0.091],[7.626,0.023]],"o":[[10.12,0.012],[9.507,-0.034],[0.07,-7.648],[-0.1,-6.569],[-7.64,-0.091],[-3.976,14.876]],"v":[[-22.548,22.478],[7.825,22.513],[22.449,11.069],[22.434,-11.875],[9.108,-22.456],[-13.797,-22.535]],"c":true},"ix":2},"nm":"Caminho 1","mn":"ADBE Vector Shape - Group","hd":false},{"ty":"fl","c":{"a":0,"k":[0.847000002394,0.039000002543,0.286000001197,1],"ix":4},"o":{"a":0,"k":100,"ix":5},"r":1,"bm":0,"nm":"Preenchimento 1","mn":"ADBE Vector Graphic - Fill","hd":false},{"ty":"tr","p":{"a":0,"k":[203.626,291.3],"ix":2},"a":{"a":0,"k":[0,0],"ix":1},"s":{"a":0,"k":[100,100],"ix":3},"r":{"a":0,"k":0,"ix":6},"o":{"a":0,"k":100,"ix":7},"sk":{"a":0,"k":0,"ix":4},"sa":{"a":0,"k":0,"ix":5},"nm":"Transformar"}],"nm":"Grupo 9","np":2,"cix":2,"bm":0,"ix":9,"mn":"ADBE Vector Group","hd":false},{"ty":"gr","it":[{"ind":0,"ty":"sh","ix":1,"ks":{"a":0,"k":{"i":[[1.243,1.101],[4.074,-0.034],[0.037,-7.81],[-0.042,-7.061],[-9.17,-0.045],[-10.101,-0.012],[-0.274,0.285],[11.095,11.944]],"o":[[-4.074,0.034],[-8.881,0.068],[-0.027,7.061],[0.037,7.834],[10.096,0.057],[0.274,-0.273],[-0.563,-14.984],[-1.085,-1.18]],"v":[[3.124,-22.54],[-9.098,-22.449],[-22.495,-10.643],[-22.495,10.541],[-8.572,22.484],[21.726,22.519],[22.537,21.689],[6.804,-19.226]],"c":true},"ix":2},"nm":"Caminho 1","mn":"ADBE Vector Shape - Group","hd":false},{"ty":"fl","c":{"a":0,"k":[0.847000002394,0.039000002543,0.286000001197,1],"ix":4},"o":{"a":0,"k":100,"ix":5},"r":1,"bm":0,"nm":"Preenchimento 1","mn":"ADBE Vector Graphic - Fill","hd":false},{"ty":"tr","p":{"a":0,"k":[635.412,291.306],"ix":2},"a":{"a":0,"k":[0,0],"ix":1},"s":{"a":0,"k":[100,100],"ix":3},"r":{"a":0,"k":0,"ix":6},"o":{"a":0,"k":100,"ix":7},"sk":{"a":0,"k":0,"ix":4},"sa":{"a":0,"k":0,"ix":5},"nm":"Transformar"}],"nm":"Grupo 10","np":2,"cix":2,"bm":0,"ix":10,"mn":"ADBE Vector Group","hd":false},{"ty":"gr","it":[{"ind":0,"ty":"sh","ix":1,"ks":{"a":0,"k":{"i":[[-15.405,0.034],[0,1.672],[0.137,7.473],[6.824,0.079],[9.707,0.012],[1.799,1.103],[0.961,-5.518],[-1.456,-6.814],[-7.099,-0.034]],"o":[[-1.401,-1.479],[-0.028,-7.473],[-0.096,-5.677],[-9.707,-0.114],[-2.018,0],[-5.615,1.217],[-1.208,6.871],[1.208,5.631],[15.391,0.091]],"v":[[30.26,18.645],[29.244,13.753],[29.175,-8.667],[18.013,-17.951],[-11.094,-17.996],[-17.011,-18.803],[-28.832,-10.352],[-28.804,10.318],[-15.926,18.713]],"c":true},"ix":2},"nm":"Caminho 1","mn":"ADBE Vector Shape - Group","hd":false},{"ty":"fl","c":{"a":0,"k":[0.847000002394,0.039000002543,0.286000001197,1],"ix":4},"o":{"a":0,"k":100,"ix":5},"r":1,"bm":0,"nm":"Preenchimento 1","mn":"ADBE Vector Graphic - Fill","hd":false},{"ty":"tr","p":{"a":0,"k":[195.877,358.912],"ix":2},"a":{"a":0,"k":[0,0],"ix":1},"s":{"a":0,"k":[100,100],"ix":3},"r":{"a":0,"k":0,"ix":6},"o":{"a":0,"k":100,"ix":7},"sk":{"a":0,"k":0,"ix":4},"sa":{"a":0,"k":0,"ix":5},"nm":"Transformar"}],"nm":"Grupo 11","np":2,"cix":2,"bm":0,"ix":11,"mn":"ADBE Vector Group","hd":false},{"ty":"gr","it":[{"ind":0,"ty":"sh","ix":1,"ks":{"a":0,"k":{"i":[[-10.112,0.033],[-0.056,8.327],[-10.127,0.022],[-9.196,-0.17],[0.093,3.047],[0.026,7.759],[2.158,0.022],[7.803,0.09],[0.056,8.779],[-0.154,6.603],[-8.062,0.397],[-3.946,2.492],[17.629,2.062],[4.224,0.419],[5.043,8.099],[12.34,20.13],[33.094,0],[44.765,0.997],[18.188,-25.917],[7.106,-14.544],[1.339,-10.071],[2.254,-7.828],[-2.173,-0.034],[-5.261,-0.227],[-0.123,-5.913],[0.109,-7.466],[8.103,-0.272],[7.46,-0.057],[2.049,-1.337],[1.271,-8.744],[-2.446,-0.034],[-8.677,-0.067],[-0.082,-7.226],[-0.137,-6.638],[-3.101,-1.054],[0,0],[-0.409,2.051],[-21.194,5.584],[0.274,-28.739],[-2.077,-1.235],[-4.195,-0.024],[-34.053,0.033],[-0.546,-2.651],[0.014,1.745],[-26.481,-0.182],[-11.039,-15.7],[-1.109,-4.87],[-2.047,-2.13]],"o":[[0.082,-8.326],[0.053,-8.257],[9.196,-0.023],[3.499,0.068],[-0.248,-7.76],[-1.803,-1.439],[-7.803,-0.068],[-10.764,-0.136],[-0.042,-6.615],[0.162,-6.707],[4.276,-0.203],[-11.832,-11.26],[-4.206,-0.486],[-11.014,-1.088],[-12.463,-20.073],[-15.071,-24.569],[-44.793,0],[-36.826,-0.815],[-9.511,13.582],[-6.312,8.677],[-2.255,7.827],[1.735,1.495],[5.26,0.079],[7.133,0.317],[0.164,7.465],[-0.096,6.74],[-7.461,0.261],[-2.351,0.022],[-1.982,8.689],[1.257,2.583],[8.677,0.124],[8.704,0.069],[0.068,6.627],[0.041,2.039],[0,0],[1.803,-1.711],[3.553,-18.169],[37.359,-9.833],[-0.013,1.619],[0.288,-3.399],[34.052,0.18],[2.445,0],[2.187,-1.326],[-0.205,-22.112],[22.234,0.146],[3.05,4.328],[0.559,2.447],[10.101,-0.069]],"v":[[193.708,118.164],[193.954,93.186],[207.961,81.757],[235.548,81.813],[240.264,78.008],[240.099,54.718],[233.828,53.551],[210.404,53.506],[195.524,41.215],[195.555,21.381],[207.878,11.083],[220.667,9.747],[176.052,-9.601],[163.331,-10.461],[139.487,-24.564],[102.087,-84.771],[29.763,-121.37],[-104.628,-121.608],[-185.672,-83.819],[-210.938,-41.839],[-222.32,-13.701],[-230.614,17.286],[-222.88,11.129],[-207.084,11.22],[-196.098,20.633],[-196.084,43.017],[-208.205,53.46],[-230.614,53.551],[-237.46,54.661],[-240.357,80.952],[-233.812,83.173],[-207.781,83.24],[-196.098,92.948],[-196.03,112.84],[-193.311,118.266],[-172.007,118.266],[-169.808,112.318],[-133.132,75.765],[-62.665,117.768],[-61.353,122.423],[-54.848,118.142],[47.308,118.221],[52.65,120.735],[54.234,115.683],[105.995,73.59],[155.459,97.105],[161.052,111.072],[163.371,118.3]],"c":true},"ix":2},"nm":"Caminho 1","mn":"ADBE Vector Shape - Group","hd":false},{"ty":"fl","c":{"a":0,"k":[0.847000002394,0.039000002543,0.286000001197,1],"ix":4},"o":{"a":0,"k":100,"ix":5},"r":1,"bm":0,"nm":"Preenchimento 1","mn":"ADBE Vector Graphic - Fill","hd":false},{"ty":"tr","p":{"a":0,"k":[417.681,258.989],"ix":2},"a":{"a":0,"k":[0,0],"ix":1},"s":{"a":0,"k":[100,100],"ix":3},"r":{"a":0,"k":0,"ix":6},"o":{"a":0,"k":100,"ix":7},"sk":{"a":0,"k":0,"ix":4},"sa":{"a":0,"k":0,"ix":5},"nm":"Transformar"}],"nm":"Grupo 12","np":2,"cix":2,"bm":0,"ix":12,"mn":"ADBE Vector Group","hd":false},{"ty":"gr","it":[{"ind":0,"ty":"sh","ix":1,"ks":{"a":0,"k":{"i":[[0,0],[4.675,0.674],[0.015,1.414],[0.042,8.08],[0.372,-0.763],[0.233,-6.543],[5.839,-0.045],[8.181,-0.09],[0.124,-8.293],[-0.052,-6.7],[-1.411,-1.425],[-15.148,-0.022],[-2.7,4.568]],"o":[[-2.069,-3.074],[-2.876,-0.405],[-0.095,-8.08],[-1.205,-0.011],[-1.081,6.521],[-0.165,4.87],[-8.186,0.078],[-10.27,0.112],[-0.094,6.699],[0.015,1.661],[15.148,0.056],[6.48,0],[0,0]],"v":[[30.086,2.564],[21.066,-4.135],[18.874,-7.681],[18.708,-31.911],[16.707,-30.452],[16.2,-10.824],[9.802,-5.482],[-14.732,-5.437],[-29.936,6.863],[-29.936,26.951],[-28.675,31.754],[16.764,31.922],[30.086,24.403]],"c":true},"ix":2},"nm":"Caminho 1","mn":"ADBE Vector Shape - Group","hd":false},{"ty":"fl","c":{"a":0,"k":[0.847000002394,0.039000002543,0.286000001197,1],"ix":4},"o":{"a":0,"k":100,"ix":5},"r":1,"bm":0,"nm":"Preenchimento 1","mn":"ADBE Vector Graphic - Fill","hd":false},{"ty":"tr","p":{"a":0,"k":[639.128,345.734],"ix":2},"a":{"a":0,"k":[0,0],"ix":1},"s":{"a":0,"k":[100,100],"ix":3},"r":{"a":0,"k":0,"ix":6},"o":{"a":0,"k":100,"ix":7},"sk":{"a":0,"k":0,"ix":4},"sa":{"a":0,"k":0,"ix":5},"nm":"Transformar"}],"nm":"Grupo 13","np":2,"cix":2,"bm":0,"ix":13,"mn":"ADBE Vector Group","hd":false}],"ip":-1.00000004073083,"op":10.0000004073084,"st":-1.00000004073083,"bm":0},{"ddd":0,"ind":10,"ty":4,"nm":"Group 9096 contornos","sr":1,"ks":{"o":{"a":0,"k":100,"ix":11},"r":{"a":0,"k":0,"ix":10},"p":{"a":0,"k":[400,426,0],"ix":2,"l":2},"a":{"a":0,"k":[421,298,0],"ix":1,"l":2},"s":{"a":0,"k":[98.575,106.04,100],"ix":6,"l":2}},"ao":0,"shapes":[{"ty":"gr","it":[{"ind":0,"ty":"sh","ix":1,"ks":{"a":0,"k":{"i":[[0,0],[1.565,-3.106],[0,-2.354]],"o":[[-3.458,1.103],[-1.093,2.16],[0,0]],"v":[[4.649,-6.571],[-3.555,-0.469],[-4.614,6.571]],"c":false},"ix":2},"nm":"Caminho 1","mn":"ADBE Vector Shape - Group","hd":false},{"ty":"st","c":{"a":0,"k":[0,0,0,1],"ix":3},"o":{"a":0,"k":100,"ix":4},"w":{"a":0,"k":3.755,"ix":5},"lc":2,"lj":1,"ml":4,"bm":0,"nm":"Traçado 1","mn":"ADBE Vector Graphic - Stroke","hd":false},{"ty":"gr","it":[{"ind":0,"ty":"sh","ix":1,"ks":{"a":0,"k":{"i":[[0,0],[1.565,-3.106],[0,-2.354]],"o":[[-3.458,1.103],[-1.093,2.16],[0,0]],"v":[[4.649,-6.571],[-3.555,-0.469],[-4.614,6.571]],"c":false},"ix":2},"nm":"Caminho 1","mn":"ADBE Vector Shape - Group","hd":false},{"ty":"st","c":{"a":0,"k":[0,0,0,1],"ix":3},"o":{"a":0,"k":100,"ix":4},"w":{"a":0,"k":3.755,"ix":5},"lc":2,"lj":1,"ml":4,"bm":0,"nm":"Traçado 1","mn":"ADBE Vector Graphic - Stroke","hd":false},{"ty":"tr","p":{"a":0,"k":[598.73,320.395],"ix":2},"a":{"a":0,"k":[0,0],"ix":1},"s":{"a":0,"k":[100,100],"ix":3},"r":{"a":0,"k":0,"ix":6},"o":{"a":0,"k":100,"ix":7},"sk":{"a":0,"k":0,"ix":4},"sa":{"a":0,"k":0,"ix":5},"nm":"Transformar"}],"nm":"Grupo 1","np":2,"cix":2,"bm":0,"ix":3,"mn":"ADBE Vector Group","hd":false},{"ty":"gr","it":[{"ind":0,"ty":"sh","ix":1,"ks":{"a":0,"k":{"i":[[0,0],[-8.545,-0.981],[-5.802,0],[-4.528,1.335]],"o":[[7.42,3.976],[5.757,0.66],[4.874,0],[0,0]],"v":[[-28.036,-3.921],[-3.765,3.261],[13.955,3.381],[28.036,0.804]],"c":false},"ix":2},"nm":"Caminho 1","mn":"ADBE Vector Shape - Group","hd":false},{"ty":"st","c":{"a":0,"k":[0,0,0,1],"ix":3},"o":{"a":0,"k":100,"ix":4},"w":{"a":0,"k":3.755,"ix":5},"lc":2,"lj":1,"ml":4,"bm":0,"nm":"Traçado 1","mn":"ADBE Vector Graphic - Stroke","hd":false},{"ty":"tr","p":{"a":0,"k":[626.158,325.255],"ix":2},"a":{"a":0,"k":[0,0],"ix":1},"s":{"a":0,"k":[100,100],"ix":3},"r":{"a":0,"k":0,"ix":6},"o":{"a":0,"k":100,"ix":7},"sk":{"a":0,"k":0,"ix":4},"sa":{"a":0,"k":0,"ix":5},"nm":"Transformar"}],"nm":"Grupo 2","np":2,"cix":2,"bm":0,"ix":4,"mn":"ADBE Vector Group","hd":false},{"ty":"tr","p":{"a":0,"k":[598.73,320.395],"ix":2},"a":{"a":0,"k":[0,0],"ix":1},"s":{"a":0,"k":[100,100],"ix":3},"r":{"a":0,"k":0,"ix":6},"o":{"a":0,"k":100,"ix":7},"sk":{"a":0,"k":0,"ix":4},"sa":{"a":0,"k":0,"ix":5},"nm":"Transformar"}],"nm":"Grupo 1","np":4,"cix":2,"bm":0,"ix":1,"mn":"ADBE Vector Group","hd":false},{"ty":"gr","it":[{"ind":0,"ty":"sh","ix":1,"ks":{"a":0,"k":{"i":[[0,0],[-8.545,-0.981],[-5.802,0],[-4.528,1.335]],"o":[[7.42,3.976],[5.757,0.66],[4.874,0],[0,0]],"v":[[-28.036,-3.921],[-3.765,3.261],[13.955,3.381],[28.036,0.804]],"c":false},"ix":2},"nm":"Caminho 1","mn":"ADBE Vector Shape - Group","hd":false},{"ty":"st","c":{"a":0,"k":[0,0,0,1],"ix":3},"o":{"a":0,"k":100,"ix":4},"w":{"a":0,"k":3.755,"ix":5},"lc":2,"lj":1,"ml":4,"bm":0,"nm":"Traçado 1","mn":"ADBE Vector Graphic - Stroke","hd":false},{"ty":"tr","p":{"a":0,"k":[626.158,325.255],"ix":2},"a":{"a":0,"k":[0,0],"ix":1},"s":{"a":0,"k":[100,100],"ix":3},"r":{"a":0,"k":0,"ix":6},"o":{"a":0,"k":100,"ix":7},"sk":{"a":0,"k":0,"ix":4},"sa":{"a":0,"k":0,"ix":5},"nm":"Transformar"}],"nm":"Grupo 2","np":2,"cix":2,"bm":0,"ix":2,"mn":"ADBE Vector Group","hd":false},{"ty":"gr","it":[{"ind":0,"ty":"sh","ix":1,"ks":{"a":0,"k":{"i":[[0,0],[-7.508,1.877],[-4.614,-2.971]],"o":[[3.777,-5.866],[7.51,-1.879],[0,0]],"v":[[-17.836,9.387],[-0.938,-7.508],[17.835,1.879]],"c":false},"ix":2},"nm":"Caminho 1","mn":"ADBE Vector Shape - Group","hd":false},{"ty":"st","c":{"a":0,"k":[0.317999985639,0,0.097999999102,1],"ix":3},"o":{"a":0,"k":100,"ix":4},"w":{"a":0,"k":7.51,"ix":5},"lc":2,"lj":1,"ml":4,"bm":0,"nm":"Traçado 1","mn":"ADBE Vector Graphic - Stroke","hd":false},{"ty":"tr","p":{"a":0,"k":[512.446,219.952],"ix":2},"a":{"a":0,"k":[0,0],"ix":1},"s":{"a":0,"k":[100,100],"ix":3},"r":{"a":0,"k":0,"ix":6},"o":{"a":0,"k":100,"ix":7},"sk":{"a":0,"k":0,"ix":4},"sa":{"a":0,"k":0,"ix":5},"nm":"Transformar"}],"nm":"Grupo 3","np":2,"cix":2,"bm":0,"ix":3,"mn":"ADBE Vector Group","hd":false},{"ty":"gr","it":[{"ind":0,"ty":"sh","ix":1,"ks":{"a":0,"k":{"i":[[0,0],[-3.975,2.429],[-3.779,0]],"o":[[0,-4.359],[3.28,-2.004],[0,0]],"v":[[-8.214,7.51],[-1.643,-5.371],[8.214,-7.51]],"c":false},"ix":2},"nm":"Caminho 1","mn":"ADBE Vector Shape - Group","hd":false},{"ty":"st","c":{"a":0,"k":[0.317999985639,0,0.097999999102,1],"ix":3},"o":{"a":0,"k":100,"ix":4},"w":{"a":0,"k":3.755,"ix":5},"lc":2,"lj":1,"ml":4,"bm":0,"nm":"Traçado 1","mn":"ADBE Vector Graphic - Stroke","hd":false},{"ty":"tr","p":{"a":0,"k":[487.806,192.728],"ix":2},"a":{"a":0,"k":[0,0],"ix":1},"s":{"a":0,"k":[100,100],"ix":3},"r":{"a":0,"k":0,"ix":6},"o":{"a":0,"k":100,"ix":7},"sk":{"a":0,"k":0,"ix":4},"sa":{"a":0,"k":0,"ix":5},"nm":"Transformar"}],"nm":"Grupo 4","np":2,"cix":2,"bm":0,"ix":4,"mn":"ADBE Vector Group","hd":false},{"ty":"gr","it":[{"ind":0,"ty":"sh","ix":1,"ks":{"a":0,"k":{"i":[[-14.952,-0.011],[-14.285,-0.31],[-0.107,6.658],[0.28,20.408],[7.896,0.034],[9.11,0.447],[9.802,-13.213],[7.242,-17.99],[-8.269,-0.023]],"o":[[14.284,0],[9.163,0.206],[0.32,-20.408],[-0.093,-6.624],[-9.136,-0.035],[-18.379,-0.905],[-11.925,16.053],[-2.707,6.715],[14.938,0.057]],"v":[[0.9,41.527],[43.767,41.608],[57.038,30.87],[57.051,-30.366],[43.567,-40.828],[16.158,-40.909],[-25.521,-22.207],[-54.651,28.659],[-43.941,41.505]],"c":true},"ix":2},"nm":"Caminho 1","mn":"ADBE Vector Shape - Group","hd":false},{"ty":"fl","c":{"a":0,"k":[1,1,1,1],"ix":4},"o":{"a":0,"k":100,"ix":5},"r":1,"bm":0,"nm":"Preenchimento 1","mn":"ADBE Vector Graphic - Fill","hd":false},{"ty":"tr","p":{"a":0,"k":[292.779,208.376],"ix":2},"a":{"a":0,"k":[0,0],"ix":1},"s":{"a":0,"k":[100,100],"ix":3},"r":{"a":0,"k":0,"ix":6},"o":{"a":0,"k":100,"ix":7},"sk":{"a":0,"k":0,"ix":4},"sa":{"a":0,"k":0,"ix":5},"nm":"Transformar"}],"nm":"Grupo 5","np":2,"cix":2,"bm":0,"ix":5,"mn":"ADBE Vector Group","hd":false},{"ty":"gr","it":[{"ind":0,"ty":"sh","ix":1,"ks":{"a":0,"k":{"i":[[-22.143,0],[-22.541,0.035],[5.59,7.567],[12.639,15.237],[22.691,0.311],[20.07,-0.011],[0,-7.579],[-0.033,-20.048],[-10.848,0]],"o":[[22.54,0],[12.407,-0.011],[-11.544,-15.674],[-11.096,-13.355],[-20.052,-0.275],[-10.98,0.012],[-0.017,20.049],[0.016,7.625],[22.125,0.012]],"v":[[-2.164,42.268],[65.474,42.256],[78.809,27.685],[45.158,-28.936],[-7.805,-40.19],[-67.996,-40.247],[-84.367,-28.936],[-84.367,31.21],[-68.56,42.268]],"c":true},"ix":2},"nm":"Caminho 1","mn":"ADBE Vector Shape - Group","hd":false},{"ty":"fl","c":{"a":0,"k":[1,1,1,1],"ix":4},"o":{"a":0,"k":100,"ix":5},"r":1,"bm":0,"nm":"Preenchimento 1","mn":"ADBE Vector Graphic - Fill","hd":false},{"ty":"tr","p":{"a":0,"k":[468.228,207.715],"ix":2},"a":{"a":0,"k":[0,0],"ix":1},"s":{"a":0,"k":[100,100],"ix":3},"r":{"a":0,"k":0,"ix":6},"o":{"a":0,"k":100,"ix":7},"sk":{"a":0,"k":0,"ix":4},"sa":{"a":0,"k":0,"ix":5},"nm":"Transformar"}],"nm":"Grupo 6","np":2,"cix":2,"bm":0,"ix":6,"mn":"ADBE Vector Group","hd":false},{"ty":"gr","it":[{"ind":0,"ty":"sh","ix":1,"ks":{"a":0,"k":{"i":[[1.34,-15.205],[-10.12,0.034],[-0.072,7.467],[0.114,7.648],[8.252,0.091],[7.626,0.023]],"o":[[10.12,0.012],[9.507,-0.034],[0.07,-7.648],[-0.1,-6.569],[-7.64,-0.091],[-3.976,14.876]],"v":[[-22.548,22.478],[7.825,22.513],[22.449,11.069],[22.434,-11.875],[9.108,-22.456],[-13.797,-22.535]],"c":true},"ix":2},"nm":"Caminho 1","mn":"ADBE Vector Shape - Group","hd":false},{"ty":"fl","c":{"a":0,"k":[0.847000002394,0.039000002543,0.286000001197,1],"ix":4},"o":{"a":0,"k":100,"ix":5},"r":1,"bm":0,"nm":"Preenchimento 1","mn":"ADBE Vector Graphic - Fill","hd":false},{"ty":"tr","p":{"a":0,"k":[203.626,291.3],"ix":2},"a":{"a":0,"k":[0,0],"ix":1},"s":{"a":0,"k":[100,100],"ix":3},"r":{"a":0,"k":0,"ix":6},"o":{"a":0,"k":100,"ix":7},"sk":{"a":0,"k":0,"ix":4},"sa":{"a":0,"k":0,"ix":5},"nm":"Transformar"}],"nm":"Grupo 7","np":2,"cix":2,"bm":0,"ix":7,"mn":"ADBE Vector Group","hd":false},{"ty":"gr","it":[{"ind":0,"ty":"sh","ix":1,"ks":{"a":0,"k":{"i":[[1.243,1.101],[4.074,-0.034],[0.037,-7.81],[-0.042,-7.061],[-9.17,-0.045],[-10.101,-0.012],[-0.274,0.285],[11.095,11.944]],"o":[[-4.074,0.034],[-8.881,0.068],[-0.027,7.061],[0.037,7.834],[10.096,0.057],[0.274,-0.273],[-0.563,-14.984],[-1.085,-1.18]],"v":[[3.124,-22.54],[-9.098,-22.449],[-22.495,-10.643],[-22.495,10.541],[-8.572,22.484],[21.726,22.519],[22.537,21.689],[6.804,-19.226]],"c":true},"ix":2},"nm":"Caminho 1","mn":"ADBE Vector Shape - Group","hd":false},{"ty":"fl","c":{"a":0,"k":[0.847000002394,0.039000002543,0.286000001197,1],"ix":4},"o":{"a":0,"k":100,"ix":5},"r":1,"bm":0,"nm":"Preenchimento 1","mn":"ADBE Vector Graphic - Fill","hd":false},{"ty":"tr","p":{"a":0,"k":[635.412,291.306],"ix":2},"a":{"a":0,"k":[0,0],"ix":1},"s":{"a":0,"k":[100,100],"ix":3},"r":{"a":0,"k":0,"ix":6},"o":{"a":0,"k":100,"ix":7},"sk":{"a":0,"k":0,"ix":4},"sa":{"a":0,"k":0,"ix":5},"nm":"Transformar"}],"nm":"Grupo 8","np":2,"cix":2,"bm":0,"ix":8,"mn":"ADBE Vector Group","hd":false},{"ty":"gr","it":[{"ind":0,"ty":"sh","ix":1,"ks":{"a":0,"k":{"i":[[-15.405,0.034],[0,1.672],[0.137,7.473],[6.824,0.079],[9.707,0.012],[1.799,1.103],[0.961,-5.518],[-1.456,-6.814],[-7.099,-0.034]],"o":[[-1.401,-1.479],[-0.028,-7.473],[-0.096,-5.677],[-9.707,-0.114],[-2.018,0],[-5.615,1.217],[-1.208,6.871],[1.208,5.631],[15.391,0.091]],"v":[[30.26,18.645],[29.244,13.753],[29.175,-8.667],[18.013,-17.951],[-11.094,-17.996],[-17.011,-18.803],[-28.832,-10.352],[-28.804,10.318],[-15.926,18.713]],"c":true},"ix":2},"nm":"Caminho 1","mn":"ADBE Vector Shape - Group","hd":false},{"ty":"fl","c":{"a":0,"k":[0.847000002394,0.039000002543,0.286000001197,1],"ix":4},"o":{"a":0,"k":100,"ix":5},"r":1,"bm":0,"nm":"Preenchimento 1","mn":"ADBE Vector Graphic - Fill","hd":false},{"ty":"tr","p":{"a":0,"k":[195.877,358.912],"ix":2},"a":{"a":0,"k":[0,0],"ix":1},"s":{"a":0,"k":[100,100],"ix":3},"r":{"a":0,"k":0,"ix":6},"o":{"a":0,"k":100,"ix":7},"sk":{"a":0,"k":0,"ix":4},"sa":{"a":0,"k":0,"ix":5},"nm":"Transformar"}],"nm":"Grupo 9","np":2,"cix":2,"bm":0,"ix":9,"mn":"ADBE Vector Group","hd":false},{"ty":"gr","it":[{"ind":0,"ty":"sh","ix":1,"ks":{"a":0,"k":{"i":[[-10.112,0.033],[-0.056,8.327],[-10.127,0.022],[-9.196,-0.17],[0.093,3.047],[0.026,7.759],[2.158,0.022],[7.803,0.09],[0.056,8.779],[-0.154,6.603],[-8.062,0.397],[-3.946,2.492],[17.629,2.062],[4.224,0.419],[5.043,8.099],[12.34,20.13],[33.094,0],[44.765,0.997],[18.188,-25.917],[7.106,-14.544],[1.339,-10.071],[2.254,-7.828],[-2.173,-0.034],[-5.261,-0.227],[-0.123,-5.913],[0.109,-7.466],[8.103,-0.272],[7.46,-0.057],[2.049,-1.337],[1.271,-8.744],[-2.446,-0.034],[-8.677,-0.067],[-0.082,-7.226],[-0.137,-6.638],[-3.101,-1.054],[0,0],[-0.409,2.051],[-21.194,5.584],[0.274,-28.739],[-2.077,-1.235],[-4.195,-0.024],[-34.053,0.033],[-0.546,-2.651],[0.014,1.745],[-26.481,-0.182],[-11.039,-15.7],[-1.109,-4.87],[-2.047,-2.13]],"o":[[0.082,-8.326],[0.053,-8.257],[9.196,-0.023],[3.499,0.068],[-0.248,-7.76],[-1.803,-1.439],[-7.803,-0.068],[-10.764,-0.136],[-0.042,-6.615],[0.162,-6.707],[4.276,-0.203],[-11.832,-11.26],[-4.206,-0.486],[-11.014,-1.088],[-12.463,-20.073],[-15.071,-24.569],[-44.793,0],[-36.826,-0.815],[-9.511,13.582],[-6.312,8.677],[-2.255,7.827],[1.735,1.495],[5.26,0.079],[7.133,0.317],[0.164,7.465],[-0.096,6.74],[-7.461,0.261],[-2.351,0.022],[-1.982,8.689],[1.257,2.583],[8.677,0.124],[8.704,0.069],[0.068,6.627],[0.041,2.039],[0,0],[1.803,-1.711],[3.553,-18.169],[37.359,-9.833],[-0.013,1.619],[0.288,-3.399],[34.052,0.18],[2.445,0],[2.187,-1.326],[-0.205,-22.112],[22.234,0.146],[3.05,4.328],[0.559,2.447],[10.101,-0.069]],"v":[[193.708,118.164],[193.954,93.186],[207.961,81.757],[235.548,81.813],[240.264,78.008],[240.099,54.718],[233.828,53.551],[210.404,53.506],[195.524,41.215],[195.555,21.381],[207.878,11.083],[220.667,9.747],[176.052,-9.601],[163.331,-10.461],[139.487,-24.564],[102.087,-84.771],[29.763,-121.37],[-104.628,-121.608],[-185.672,-83.819],[-210.938,-41.839],[-222.32,-13.701],[-230.614,17.286],[-222.88,11.129],[-207.084,11.22],[-196.098,20.633],[-196.084,43.017],[-208.205,53.46],[-230.614,53.551],[-237.46,54.661],[-240.357,80.952],[-233.812,83.173],[-207.781,83.24],[-196.098,92.948],[-196.03,112.84],[-193.311,118.266],[-172.007,118.266],[-169.808,112.318],[-133.132,75.765],[-62.665,117.768],[-61.353,122.423],[-54.848,118.142],[47.308,118.221],[52.65,120.735],[54.234,115.683],[105.995,73.59],[155.459,97.105],[161.052,111.072],[163.371,118.3]],"c":true},"ix":2},"nm":"Caminho 1","mn":"ADBE Vector Shape - Group","hd":false},{"ty":"fl","c":{"a":0,"k":[0.847000002394,0.039000002543,0.286000001197,1],"ix":4},"o":{"a":0,"k":100,"ix":5},"r":1,"bm":0,"nm":"Preenchimento 1","mn":"ADBE Vector Graphic - Fill","hd":false},{"ty":"tr","p":{"a":0,"k":[417.681,258.989],"ix":2},"a":{"a":0,"k":[0,0],"ix":1},"s":{"a":0,"k":[100,100],"ix":3},"r":{"a":0,"k":0,"ix":6},"o":{"a":0,"k":100,"ix":7},"sk":{"a":0,"k":0,"ix":4},"sa":{"a":0,"k":0,"ix":5},"nm":"Transformar"}],"nm":"Grupo 10","np":2,"cix":2,"bm":0,"ix":10,"mn":"ADBE Vector Group","hd":false},{"ty":"gr","it":[{"ind":0,"ty":"sh","ix":1,"ks":{"a":0,"k":{"i":[[0,0],[4.675,0.674],[0.015,1.414],[0.042,8.08],[0.372,-0.763],[0.233,-6.543],[5.839,-0.045],[8.181,-0.09],[0.124,-8.293],[-0.052,-6.7],[-1.411,-1.425],[-15.148,-0.022],[-2.7,4.568]],"o":[[-2.069,-3.074],[-2.876,-0.405],[-0.095,-8.08],[-1.205,-0.011],[-1.081,6.521],[-0.165,4.87],[-8.186,0.078],[-10.27,0.112],[-0.094,6.699],[0.015,1.661],[15.148,0.056],[6.48,0],[0,0]],"v":[[30.086,2.564],[21.066,-4.135],[18.874,-7.681],[18.708,-31.911],[16.707,-30.452],[16.2,-10.824],[9.802,-5.482],[-14.732,-5.437],[-29.936,6.863],[-29.936,26.951],[-28.675,31.754],[16.764,31.922],[30.086,24.403]],"c":true},"ix":2},"nm":"Caminho 1","mn":"ADBE Vector Shape - Group","hd":false},{"ty":"fl","c":{"a":0,"k":[0.847000002394,0.039000002543,0.286000001197,1],"ix":4},"o":{"a":0,"k":100,"ix":5},"r":1,"bm":0,"nm":"Preenchimento 1","mn":"ADBE Vector Graphic - Fill","hd":false},{"ty":"tr","p":{"a":0,"k":[639.128,345.734],"ix":2},"a":{"a":0,"k":[0,0],"ix":1},"s":{"a":0,"k":[100,100],"ix":3},"r":{"a":0,"k":0,"ix":6},"o":{"a":0,"k":100,"ix":7},"sk":{"a":0,"k":0,"ix":4},"sa":{"a":0,"k":0,"ix":5},"nm":"Transformar"}],"nm":"Grupo 11","np":2,"cix":2,"bm":0,"ix":11,"mn":"ADBE Vector Group","hd":false}],"ip":10.0000004073083,"op":16.0000006516934,"st":10.0000004073083,"bm":0},{"ddd":0,"ind":11,"ty":4,"nm":"Group 7075 contornos 2","sr":1,"ks":{"o":{"a":0,"k":100,"ix":11},"r":{"a":0,"k":0,"ix":10},"p":{"a":1,"k":[{"i":{"x":0.833,"y":0.833},"o":{"x":0.167,"y":0.167},"t":18,"s":[400,426,0],"to":[0,0.333,0],"ti":[0,-0.333,0]},{"t":23.0000009368092,"s":[400,428,0]}],"ix":2,"l":2},"a":{"a":0,"k":[421,298,0],"ix":1,"l":2},"s":{"a":0,"k":[98.42,105.302,100],"ix":6,"l":2}},"ao":0,"shapes":[{"ty":"gr","it":[{"ind":0,"ty":"sh","ix":1,"ks":{"a":0,"k":{"i":[[-1.471,0.172],[-0.172,-1.471],[1.47,-0.171],[0.171,1.47]],"o":[[1.47,-0.171],[0.171,1.47],[-1.471,0.172],[-0.171,-1.471]],"v":[[-0.31,-2.663],[2.662,-0.31],[0.31,2.661],[-2.663,0.311]],"c":true},"ix":2},"nm":"Caminho 1","mn":"ADBE Vector Shape - Group","hd":false},{"ty":"fl","c":{"a":0,"k":[1,1,1,1],"ix":4},"o":{"a":0,"k":100,"ix":5},"r":1,"bm":0,"nm":"Preenchimento 1","mn":"ADBE Vector Graphic - Fill","hd":false},{"ty":"tr","p":{"a":0,"k":[520.932,226.257],"ix":2},"a":{"a":0,"k":[0,0],"ix":1},"s":{"a":0,"k":[100,100],"ix":3},"r":{"a":0,"k":0,"ix":6},"o":{"a":0,"k":100,"ix":7},"sk":{"a":0,"k":0,"ix":4},"sa":{"a":0,"k":0,"ix":5},"nm":"Transformar"}],"nm":"Grupo 1","np":2,"cix":2,"bm":0,"ix":1,"mn":"ADBE Vector Group","hd":false},{"ty":"gr","it":[{"ind":0,"ty":"sh","ix":1,"ks":{"a":0,"k":{"i":[[-2.94,0.343],[-0.342,-2.94],[2.941,-0.343],[0.344,2.941]],"o":[[2.94,-0.343],[0.343,2.941],[-2.94,0.343],[-0.343,-2.94]],"v":[[-0.621,-5.324],[5.324,-0.621],[0.621,5.324],[-5.324,0.621]],"c":true},"ix":2},"nm":"Caminho 1","mn":"ADBE Vector Shape - Group","hd":false},{"ty":"fl","c":{"a":0,"k":[1,1,1,1],"ix":4},"o":{"a":0,"k":100,"ix":5},"r":1,"bm":0,"nm":"Preenchimento 1","mn":"ADBE Vector Graphic - Fill","hd":false},{"ty":"tr","p":{"a":0,"k":[520.266,214.681],"ix":2},"a":{"a":0,"k":[0,0],"ix":1},"s":{"a":0,"k":[100,100],"ix":3},"r":{"a":0,"k":0,"ix":6},"o":{"a":0,"k":100,"ix":7},"sk":{"a":0,"k":0,"ix":4},"sa":{"a":0,"k":0,"ix":5},"nm":"Transformar"}],"nm":"Grupo 2","np":2,"cix":2,"bm":0,"ix":2,"mn":"ADBE Vector Group","hd":false},{"ty":"gr","it":[{"ind":0,"ty":"sh","ix":1,"ks":{"a":0,"k":{"i":[[-8.821,1.029],[-1.63,-13.967],[8.822,-1.029],[1.628,13.968]],"o":[[8.821,-1.029],[1.629,13.967],[-8.821,1.029],[-1.63,-13.966]],"v":[[-2.951,-25.29],[15.972,-1.863],[2.949,25.29],[-15.972,1.863]],"c":true},"ix":2},"nm":"Caminho 1","mn":"ADBE Vector Shape - Group","hd":false},{"ty":"fl","c":{"a":0,"k":[0.317999985639,0,0.097999999102,1],"ix":4},"o":{"a":0,"k":100,"ix":5},"r":1,"bm":0,"nm":"Preenchimento 1","mn":"ADBE Vector Graphic - Fill","hd":false},{"ty":"tr","p":{"a":0,"k":[512.265,220.661],"ix":2},"a":{"a":0,"k":[0,0],"ix":1},"s":{"a":0,"k":[100,100],"ix":3},"r":{"a":0,"k":0,"ix":6},"o":{"a":0,"k":100,"ix":7},"sk":{"a":0,"k":0,"ix":4},"sa":{"a":0,"k":0,"ix":5},"nm":"Transformar"}],"nm":"Grupo 3","np":2,"cix":2,"bm":0,"ix":3,"mn":"ADBE Vector Group","hd":false},{"ty":"gr","it":[{"ind":0,"ty":"sh","ix":1,"ks":{"a":0,"k":{"i":[[0,0],[1.565,-3.106],[0,-2.354]],"o":[[-3.458,1.103],[-1.093,2.16],[0,0]],"v":[[4.649,-6.571],[-3.555,-0.469],[-4.614,6.571]],"c":false},"ix":2},"nm":"Caminho 1","mn":"ADBE Vector Shape - Group","hd":false},{"ty":"st","c":{"a":0,"k":[0,0,0,1],"ix":3},"o":{"a":0,"k":100,"ix":4},"w":{"a":0,"k":3.755,"ix":5},"lc":2,"lj":1,"ml":4,"bm":0,"nm":"Traçado 1","mn":"ADBE Vector Graphic - Stroke","hd":false},{"ty":"tr","p":{"a":0,"k":[598.73,320.395],"ix":2},"a":{"a":0,"k":[0,0],"ix":1},"s":{"a":0,"k":[100,100],"ix":3},"r":{"a":0,"k":0,"ix":6},"o":{"a":0,"k":100,"ix":7},"sk":{"a":0,"k":0,"ix":4},"sa":{"a":0,"k":0,"ix":5},"nm":"Transformar"}],"nm":"Grupo 4","np":2,"cix":2,"bm":0,"ix":4,"mn":"ADBE Vector Group","hd":false},{"ty":"gr","it":[{"ind":0,"ty":"sh","ix":1,"ks":{"a":0,"k":{"i":[[0,0],[-8.545,-0.981],[-5.802,0],[-4.528,1.335]],"o":[[7.42,3.976],[5.757,0.66],[4.874,0],[0,0]],"v":[[-28.036,-3.921],[-3.765,3.261],[13.955,3.381],[28.036,0.804]],"c":false},"ix":2},"nm":"Caminho 1","mn":"ADBE Vector Shape - Group","hd":false},{"ty":"st","c":{"a":0,"k":[0,0,0,1],"ix":3},"o":{"a":0,"k":100,"ix":4},"w":{"a":0,"k":3.755,"ix":5},"lc":2,"lj":1,"ml":4,"bm":0,"nm":"Traçado 1","mn":"ADBE Vector Graphic - Stroke","hd":false},{"ty":"tr","p":{"a":0,"k":[626.158,325.255],"ix":2},"a":{"a":0,"k":[0,0],"ix":1},"s":{"a":0,"k":[100,100],"ix":3},"r":{"a":0,"k":0,"ix":6},"o":{"a":0,"k":100,"ix":7},"sk":{"a":0,"k":0,"ix":4},"sa":{"a":0,"k":0,"ix":5},"nm":"Transformar"}],"nm":"Grupo 5","np":2,"cix":2,"bm":0,"ix":5,"mn":"ADBE Vector Group","hd":false},{"ty":"gr","it":[{"ind":0,"ty":"sh","ix":1,"ks":{"a":0,"k":{"i":[[0,0],[-3.975,2.429],[-3.779,0]],"o":[[0,-4.359],[3.28,-2.004],[0,0]],"v":[[-8.214,7.51],[-1.643,-5.371],[8.214,-7.51]],"c":false},"ix":2},"nm":"Caminho 1","mn":"ADBE Vector Shape - Group","hd":false},{"ty":"st","c":{"a":0,"k":[0.317999985639,0,0.097999999102,1],"ix":3},"o":{"a":0,"k":100,"ix":4},"w":{"a":0,"k":3.755,"ix":5},"lc":2,"lj":1,"ml":4,"bm":0,"nm":"Traçado 1","mn":"ADBE Vector Graphic - Stroke","hd":false},{"ty":"tr","p":{"a":0,"k":[487.806,192.728],"ix":2},"a":{"a":0,"k":[0,0],"ix":1},"s":{"a":0,"k":[100,100],"ix":3},"r":{"a":0,"k":0,"ix":6},"o":{"a":0,"k":100,"ix":7},"sk":{"a":0,"k":0,"ix":4},"sa":{"a":0,"k":0,"ix":5},"nm":"Transformar"}],"nm":"Grupo 6","np":2,"cix":2,"bm":0,"ix":6,"mn":"ADBE Vector Group","hd":false},{"ty":"gr","it":[{"ind":0,"ty":"sh","ix":1,"ks":{"a":0,"k":{"i":[[-14.952,-0.011],[-14.285,-0.31],[-0.107,6.658],[0.28,20.408],[7.896,0.034],[9.11,0.447],[9.802,-13.213],[7.242,-17.99],[-8.269,-0.023]],"o":[[14.284,0],[9.163,0.206],[0.32,-20.408],[-0.093,-6.624],[-9.136,-0.035],[-18.379,-0.905],[-11.925,16.053],[-2.707,6.715],[14.938,0.057]],"v":[[0.9,41.527],[43.767,41.608],[57.038,30.87],[57.051,-30.366],[43.567,-40.828],[16.158,-40.909],[-25.521,-22.207],[-54.651,28.659],[-43.941,41.505]],"c":true},"ix":2},"nm":"Caminho 1","mn":"ADBE Vector Shape - Group","hd":false},{"ty":"fl","c":{"a":0,"k":[1,1,1,1],"ix":4},"o":{"a":0,"k":100,"ix":5},"r":1,"bm":0,"nm":"Preenchimento 1","mn":"ADBE Vector Graphic - Fill","hd":false},{"ty":"tr","p":{"a":0,"k":[292.779,208.376],"ix":2},"a":{"a":0,"k":[0,0],"ix":1},"s":{"a":0,"k":[100,100],"ix":3},"r":{"a":0,"k":0,"ix":6},"o":{"a":0,"k":100,"ix":7},"sk":{"a":0,"k":0,"ix":4},"sa":{"a":0,"k":0,"ix":5},"nm":"Transformar"}],"nm":"Grupo 7","np":2,"cix":2,"bm":0,"ix":7,"mn":"ADBE Vector Group","hd":false},{"ty":"gr","it":[{"ind":0,"ty":"sh","ix":1,"ks":{"a":0,"k":{"i":[[-22.143,0],[-22.541,0.035],[5.59,7.567],[12.639,15.237],[22.691,0.311],[20.07,-0.011],[0,-7.579],[-0.033,-20.048],[-10.848,0]],"o":[[22.54,0],[12.407,-0.011],[-11.544,-15.674],[-11.096,-13.355],[-20.052,-0.275],[-10.98,0.012],[-0.017,20.049],[0.016,7.625],[22.125,0.012]],"v":[[-2.164,42.268],[65.474,42.256],[78.809,27.685],[45.158,-28.936],[-7.805,-40.19],[-67.996,-40.247],[-84.367,-28.936],[-84.367,31.21],[-68.56,42.268]],"c":true},"ix":2},"nm":"Caminho 1","mn":"ADBE Vector Shape - Group","hd":false},{"ty":"fl","c":{"a":0,"k":[1,1,1,1],"ix":4},"o":{"a":0,"k":100,"ix":5},"r":1,"bm":0,"nm":"Preenchimento 1","mn":"ADBE Vector Graphic - Fill","hd":false},{"ty":"tr","p":{"a":0,"k":[468.228,207.715],"ix":2},"a":{"a":0,"k":[0,0],"ix":1},"s":{"a":0,"k":[100,100],"ix":3},"r":{"a":0,"k":0,"ix":6},"o":{"a":0,"k":100,"ix":7},"sk":{"a":0,"k":0,"ix":4},"sa":{"a":0,"k":0,"ix":5},"nm":"Transformar"}],"nm":"Grupo 8","np":2,"cix":2,"bm":0,"ix":8,"mn":"ADBE Vector Group","hd":false},{"ty":"gr","it":[{"ind":0,"ty":"sh","ix":1,"ks":{"a":0,"k":{"i":[[1.34,-15.205],[-10.12,0.034],[-0.072,7.467],[0.114,7.648],[8.252,0.091],[7.626,0.023]],"o":[[10.12,0.012],[9.507,-0.034],[0.07,-7.648],[-0.1,-6.569],[-7.64,-0.091],[-3.976,14.876]],"v":[[-22.548,22.478],[7.825,22.513],[22.449,11.069],[22.434,-11.875],[9.108,-22.456],[-13.797,-22.535]],"c":true},"ix":2},"nm":"Caminho 1","mn":"ADBE Vector Shape - Group","hd":false},{"ty":"fl","c":{"a":0,"k":[0.847000002394,0.039000002543,0.286000001197,1],"ix":4},"o":{"a":0,"k":100,"ix":5},"r":1,"bm":0,"nm":"Preenchimento 1","mn":"ADBE Vector Graphic - Fill","hd":false},{"ty":"tr","p":{"a":0,"k":[203.626,291.3],"ix":2},"a":{"a":0,"k":[0,0],"ix":1},"s":{"a":0,"k":[100,100],"ix":3},"r":{"a":0,"k":0,"ix":6},"o":{"a":0,"k":100,"ix":7},"sk":{"a":0,"k":0,"ix":4},"sa":{"a":0,"k":0,"ix":5},"nm":"Transformar"}],"nm":"Grupo 9","np":2,"cix":2,"bm":0,"ix":9,"mn":"ADBE Vector Group","hd":false},{"ty":"gr","it":[{"ind":0,"ty":"sh","ix":1,"ks":{"a":0,"k":{"i":[[1.243,1.101],[4.074,-0.034],[0.037,-7.81],[-0.042,-7.061],[-9.17,-0.045],[-10.101,-0.012],[-0.274,0.285],[11.095,11.944]],"o":[[-4.074,0.034],[-8.881,0.068],[-0.027,7.061],[0.037,7.834],[10.096,0.057],[0.274,-0.273],[-0.563,-14.984],[-1.085,-1.18]],"v":[[3.124,-22.54],[-9.098,-22.449],[-22.495,-10.643],[-22.495,10.541],[-8.572,22.484],[21.726,22.519],[22.537,21.689],[6.804,-19.226]],"c":true},"ix":2},"nm":"Caminho 1","mn":"ADBE Vector Shape - Group","hd":false},{"ty":"fl","c":{"a":0,"k":[0.847000002394,0.039000002543,0.286000001197,1],"ix":4},"o":{"a":0,"k":100,"ix":5},"r":1,"bm":0,"nm":"Preenchimento 1","mn":"ADBE Vector Graphic - Fill","hd":false},{"ty":"tr","p":{"a":0,"k":[635.412,291.306],"ix":2},"a":{"a":0,"k":[0,0],"ix":1},"s":{"a":0,"k":[100,100],"ix":3},"r":{"a":0,"k":0,"ix":6},"o":{"a":0,"k":100,"ix":7},"sk":{"a":0,"k":0,"ix":4},"sa":{"a":0,"k":0,"ix":5},"nm":"Transformar"}],"nm":"Grupo 10","np":2,"cix":2,"bm":0,"ix":10,"mn":"ADBE Vector Group","hd":false},{"ty":"gr","it":[{"ind":0,"ty":"sh","ix":1,"ks":{"a":0,"k":{"i":[[-15.405,0.034],[0,1.672],[0.137,7.473],[6.824,0.079],[9.707,0.012],[1.799,1.103],[0.961,-5.518],[-1.456,-6.814],[-7.099,-0.034]],"o":[[-1.401,-1.479],[-0.028,-7.473],[-0.096,-5.677],[-9.707,-0.114],[-2.018,0],[-5.615,1.217],[-1.208,6.871],[1.208,5.631],[15.391,0.091]],"v":[[30.26,18.645],[29.244,13.753],[29.175,-8.667],[18.013,-17.951],[-11.094,-17.996],[-17.011,-18.803],[-28.832,-10.352],[-28.804,10.318],[-15.926,18.713]],"c":true},"ix":2},"nm":"Caminho 1","mn":"ADBE Vector Shape - Group","hd":false},{"ty":"fl","c":{"a":0,"k":[0.847000002394,0.039000002543,0.286000001197,1],"ix":4},"o":{"a":0,"k":100,"ix":5},"r":1,"bm":0,"nm":"Preenchimento 1","mn":"ADBE Vector Graphic - Fill","hd":false},{"ty":"tr","p":{"a":0,"k":[195.877,358.912],"ix":2},"a":{"a":0,"k":[0,0],"ix":1},"s":{"a":0,"k":[100,100],"ix":3},"r":{"a":0,"k":0,"ix":6},"o":{"a":0,"k":100,"ix":7},"sk":{"a":0,"k":0,"ix":4},"sa":{"a":0,"k":0,"ix":5},"nm":"Transformar"}],"nm":"Grupo 11","np":2,"cix":2,"bm":0,"ix":11,"mn":"ADBE Vector Group","hd":false},{"ty":"gr","it":[{"ind":0,"ty":"sh","ix":1,"ks":{"a":0,"k":{"i":[[-10.112,0.033],[-0.056,8.327],[-10.127,0.022],[-9.196,-0.17],[0.093,3.047],[0.026,7.759],[2.158,0.022],[7.803,0.09],[0.056,8.779],[-0.154,6.603],[-8.062,0.397],[-3.946,2.492],[17.629,2.062],[4.224,0.419],[5.043,8.099],[12.34,20.13],[33.094,0],[44.765,0.997],[18.188,-25.917],[7.106,-14.544],[1.339,-10.071],[2.254,-7.828],[-2.173,-0.034],[-5.261,-0.227],[-0.123,-5.913],[0.109,-7.466],[8.103,-0.272],[7.46,-0.057],[2.049,-1.337],[1.271,-8.744],[-2.446,-0.034],[-8.677,-0.067],[-0.082,-7.226],[-0.137,-6.638],[-3.101,-1.054],[0,0],[-0.409,2.051],[-21.194,5.584],[0.274,-28.739],[-2.077,-1.235],[-4.195,-0.024],[-34.053,0.033],[-0.546,-2.651],[0.014,1.745],[-26.481,-0.182],[-11.039,-15.7],[-1.109,-4.87],[-2.047,-2.13]],"o":[[0.082,-8.326],[0.053,-8.257],[9.196,-0.023],[3.499,0.068],[-0.248,-7.76],[-1.803,-1.439],[-7.803,-0.068],[-10.764,-0.136],[-0.042,-6.615],[0.162,-6.707],[4.276,-0.203],[-11.832,-11.26],[-4.206,-0.486],[-11.014,-1.088],[-12.463,-20.073],[-15.071,-24.569],[-44.793,0],[-36.826,-0.815],[-9.511,13.582],[-6.312,8.677],[-2.255,7.827],[1.735,1.495],[5.26,0.079],[7.133,0.317],[0.164,7.465],[-0.096,6.74],[-7.461,0.261],[-2.351,0.022],[-1.982,8.689],[1.257,2.583],[8.677,0.124],[8.704,0.069],[0.068,6.627],[0.041,2.039],[0,0],[1.803,-1.711],[3.553,-18.169],[37.359,-9.833],[-0.013,1.619],[0.288,-3.399],[34.052,0.18],[2.445,0],[2.187,-1.326],[-0.205,-22.112],[22.234,0.146],[3.05,4.328],[0.559,2.447],[10.101,-0.069]],"v":[[193.708,118.164],[193.954,93.186],[207.961,81.757],[235.548,81.813],[240.264,78.008],[240.099,54.718],[233.828,53.551],[210.404,53.506],[195.524,41.215],[195.555,21.381],[207.878,11.083],[220.667,9.747],[176.052,-9.601],[163.331,-10.461],[139.487,-24.564],[102.087,-84.771],[29.763,-121.37],[-104.628,-121.608],[-185.672,-83.819],[-210.938,-41.839],[-222.32,-13.701],[-230.614,17.286],[-222.88,11.129],[-207.084,11.22],[-196.098,20.633],[-196.084,43.017],[-208.205,53.46],[-230.614,53.551],[-237.46,54.661],[-240.357,80.952],[-233.812,83.173],[-207.781,83.24],[-196.098,92.948],[-196.03,112.84],[-193.311,118.266],[-172.007,118.266],[-169.808,112.318],[-133.132,75.765],[-62.665,117.768],[-61.353,122.423],[-54.848,118.142],[47.308,118.221],[52.65,120.735],[54.234,115.683],[105.995,73.59],[155.459,97.105],[161.052,111.072],[163.371,118.3]],"c":true},"ix":2},"nm":"Caminho 1","mn":"ADBE Vector Shape - Group","hd":false},{"ty":"fl","c":{"a":0,"k":[0.847000002394,0.039000002543,0.286000001197,1],"ix":4},"o":{"a":0,"k":100,"ix":5},"r":1,"bm":0,"nm":"Preenchimento 1","mn":"ADBE Vector Graphic - Fill","hd":false},{"ty":"tr","p":{"a":0,"k":[417.681,258.989],"ix":2},"a":{"a":0,"k":[0,0],"ix":1},"s":{"a":0,"k":[100,100],"ix":3},"r":{"a":0,"k":0,"ix":6},"o":{"a":0,"k":100,"ix":7},"sk":{"a":0,"k":0,"ix":4},"sa":{"a":0,"k":0,"ix":5},"nm":"Transformar"}],"nm":"Grupo 12","np":2,"cix":2,"bm":0,"ix":12,"mn":"ADBE Vector Group","hd":false},{"ty":"gr","it":[{"ind":0,"ty":"sh","ix":1,"ks":{"a":0,"k":{"i":[[0,0],[4.675,0.674],[0.015,1.414],[0.042,8.08],[0.372,-0.763],[0.233,-6.543],[5.839,-0.045],[8.181,-0.09],[0.124,-8.293],[-0.052,-6.7],[-1.411,-1.425],[-15.148,-0.022],[-2.7,4.568]],"o":[[-2.069,-3.074],[-2.876,-0.405],[-0.095,-8.08],[-1.205,-0.011],[-1.081,6.521],[-0.165,4.87],[-8.186,0.078],[-10.27,0.112],[-0.094,6.699],[0.015,1.661],[15.148,0.056],[6.48,0],[0,0]],"v":[[30.086,2.564],[21.066,-4.135],[18.874,-7.681],[18.708,-31.911],[16.707,-30.452],[16.2,-10.824],[9.802,-5.482],[-14.732,-5.437],[-29.936,6.863],[-29.936,26.951],[-28.675,31.754],[16.764,31.922],[30.086,24.403]],"c":true},"ix":2},"nm":"Caminho 1","mn":"ADBE Vector Shape - Group","hd":false},{"ty":"fl","c":{"a":0,"k":[0.847000002394,0.039000002543,0.286000001197,1],"ix":4},"o":{"a":0,"k":100,"ix":5},"r":1,"bm":0,"nm":"Preenchimento 1","mn":"ADBE Vector Graphic - Fill","hd":false},{"ty":"tr","p":{"a":0,"k":[639.128,345.734],"ix":2},"a":{"a":0,"k":[0,0],"ix":1},"s":{"a":0,"k":[100,100],"ix":3},"r":{"a":0,"k":0,"ix":6},"o":{"a":0,"k":100,"ix":7},"sk":{"a":0,"k":0,"ix":4},"sa":{"a":0,"k":0,"ix":5},"nm":"Transformar"}],"nm":"Grupo 13","np":2,"cix":2,"bm":0,"ix":13,"mn":"ADBE Vector Group","hd":false}],"ip":16.0000006516934,"op":25.0000010182709,"st":14.0000005702317,"bm":0}],"markers":[]}